<code object <module> at 0x000001CAC3E2EF70, file "app\services\call_session_manager.py", line 1>


Disassembling code object: <module> at app\services\call_session_manager.py
Constants: (0, None, ('datetime', 'timezone'), ('Dict', 'Any', 'Optional', 'Callable'), ('get_supabase_client',), <code object CallSessionManager at 0x000001CAC4254B20, file "app\services\call_session_manager.py", line 9>, 'CallSessionManager')
Names: ('logging', 'datetime', 'timezone', 'typing', 'Dict', 'Any', 'Optional', 'Callable', 'app.db.client', 'get_supabase_client', 'asyncio', 'getLogger', '__name__', 'logger', 'CallSessionManager', 'call_session_manager')
Varnames: ()
  0           0 RESUME                   0

  1           2 LOAD_CONST               0 (0)
              4 LOAD_CONST               1 (None)
              6 IMPORT_NAME              0 (logging)
              8 STORE_NAME               0 (logging)

  2          10 LOAD_CONST               0 (0)
             12 LOAD_CONST               2 (('datetime', 'timezone'))
             14 IMPORT_NAME              1 (datetime)
             16 IMPORT_FROM              1 (datetime)
             18 STORE_NAME               1 (datetime)
             20 IMPORT_FROM              2 (timezone)
             22 STORE_NAME               2 (timezone)
             24 POP_TOP

  3          26 LOAD_CONST               0 (0)
             28 LOAD_CONST               3 (('Dict', 'Any', 'Optional', 'Callable'))
             30 IMPORT_NAME              3 (typing)
             32 IMPORT_FROM              4 (Dict)
             34 STORE_NAME               4 (Dict)
             36 IMPORT_FROM              5 (Any)
             38 STORE_NAME               5 (Any)
             40 IMPORT_FROM              6 (Optional)
             42 STORE_NAME               6 (Optional)
             44 IMPORT_FROM              7 (Callable)
             46 STORE_NAME               7 (Callable)
             48 POP_TOP

  4          50 LOAD_CONST               0 (0)
             52 LOAD_CONST               4 (('get_supabase_client',))
             54 IMPORT_NAME              8 (app.db.client)
             56 IMPORT_FROM              9 (get_supabase_client)
             58 STORE_NAME               9 (get_supabase_client)
             60 POP_TOP

  5          62 LOAD_CONST               0 (0)
             64 LOAD_CONST               1 (None)
             66 IMPORT_NAME             10 (asyncio)
             68 STORE_NAME              10 (asyncio)

  7          70 PUSH_NULL
             72 LOAD_NAME                0 (logging)
             74 LOAD_ATTR               22 (getLogger)
             94 LOAD_NAME               12 (__name__)
             96 CALL                     1
            104 STORE_NAME              13 (logger)

  9         106 PUSH_NULL
            108 LOAD_BUILD_CLASS
            110 LOAD_CONST               5 (<code object CallSessionManager at 0x000001CAC4254B20, file "app\services\call_session_manager.py", line 9>)
            112 MAKE_FUNCTION            0
            114 LOAD_CONST               6 ('CallSessionManager')
            116 CALL                     2
            124 STORE_NAME              14 (CallSessionManager)

205         126 PUSH_NULL
            128 LOAD_NAME               14 (CallSessionManager)
            130 CALL                     0
            138 STORE_NAME              15 (call_session_manager)
            140 RETURN_CONST             1 (None)

Disassembly of <code object CallSessionManager at 0x000001CAC4254B20, file "app\services\call_session_manager.py", line 9>:
              0 MAKE_CELL                0 (__class__)

  9           2 RESUME                   0
              4 LOAD_NAME                0 (__name__)
              6 STORE_NAME               1 (__module__)
              8 LOAD_CONST               0 ('CallSessionManager')
             10 STORE_NAME               2 (__qualname__)

 10          12 LOAD_CONST               1 (None)
             14 STORE_NAME               3 (_instance)

 12          16 LOAD_CLOSURE             0 (__class__)
             18 BUILD_TUPLE              1
             20 LOAD_CONST               2 (<code object __new__ at 0x000001CAC3DF10B0, file "app\services\call_session_manager.py", line 12>)
             22 MAKE_FUNCTION            8 (closure)
             24 STORE_NAME               4 (__new__)

 18          26 LOAD_CONST               3 (<code object _init at 0x000001CAC419BBB0, file "app\services\call_session_manager.py", line 18>)
             28 MAKE_FUNCTION            0
             30 STORE_NAME               5 (_init)

 24          32 LOAD_CONST               4 ('call_uuid')

 26          34 LOAD_NAME                6 (str)

 24          36 LOAD_CONST               5 ('caller_id')

 27          38 LOAD_NAME                6 (str)

 24          40 LOAD_CONST               6 ('dialed_number')

 28          42 LOAD_NAME                6 (str)

 24          44 LOAD_CONST               7 ('workspace_id')

 29          46 LOAD_NAME                6 (str)

 24          48 LOAD_CONST               8 ('agent_id')

 30          50 LOAD_NAME                6 (str)

 24          52 LOAD_CONST               9 ('phone_number_id')

 31          54 LOAD_NAME                6 (str)

 24          56 LOAD_CONST              10 ('return')

 32          58 LOAD_NAME                7 (Dict)
             60 LOAD_NAME                6 (str)
             62 LOAD_NAME                8 (Any)
             64 BUILD_TUPLE              2
             66 BINARY_SUBSCR

 24          70 BUILD_TUPLE             14
             72 LOAD_CONST              11 (<code object register_inbound_asterisk_call at 0x000001CAC3DED6F0, file "app\services\call_session_manager.py", line 24>)
             74 MAKE_FUNCTION            4 (annotations)
             76 STORE_NAME               9 (register_inbound_asterisk_call)

 56          78 LOAD_CONST               4 ('call_uuid')
             80 LOAD_NAME                6 (str)
             82 LOAD_CONST              10 ('return')
             84 LOAD_NAME               10 (Optional)
             86 LOAD_NAME                7 (Dict)
             88 LOAD_NAME                6 (str)
             90 LOAD_NAME                8 (Any)
             92 BUILD_TUPLE              2
             94 BINARY_SUBSCR
             98 BINARY_SUBSCR
            102 BUILD_TUPLE              4
            104 LOAD_CONST              12 (<code object get_call_context at 0x000001CAC40EFDB0, file "app\services\call_session_manager.py", line 56>)
            106 MAKE_FUNCTION            4 (annotations)
            108 STORE_NAME              11 (get_call_context)

116         110 LOAD_CONST               4 ('call_uuid')
            112 LOAD_NAME                6 (str)
            114 LOAD_CONST              10 ('return')
            116 LOAD_NAME               12 (bool)
            118 BUILD_TUPLE              4
            120 LOAD_CONST              13 (<code object start_audio_session at 0x000001CAC3C38AF0, file "app\services\call_session_manager.py", line 116>)
            122 MAKE_FUNCTION            4 (annotations)
            124 STORE_NAME              13 (start_audio_session)

141         126 LOAD_CONST              19 (('hangup',))
            128 LOAD_CONST               4 ('call_uuid')
            130 LOAD_NAME                6 (str)
            132 LOAD_CONST              14 ('reason')
            134 LOAD_NAME                6 (str)
            136 LOAD_CONST              10 ('return')
            138 LOAD_NAME               12 (bool)
            140 BUILD_TUPLE              6
            142 LOAD_CONST              15 (<code object end_call at 0x000001CAC3C3A830, file "app\services\call_session_manager.py", line 141>)
            144 MAKE_FUNCTION            5 (defaults, annotations)
            146 STORE_NAME              14 (end_call)

183         148 LOAD_CONST               4 ('call_uuid')
            150 LOAD_NAME                6 (str)
            152 LOAD_CONST              16 ('callback')
            154 LOAD_NAME               15 (Callable)
            156 LOAD_NAME                6 (str)
            158 BUILD_LIST               1
            160 LOAD_CONST               1 (None)
            162 BUILD_TUPLE              2
            164 BINARY_SUBSCR
            168 BUILD_TUPLE              4
            170 LOAD_CONST              17 (<code object register_cleanup_callback at 0x000001CAC42054D0, file "app\services\call_session_manager.py", line 183>)
            172 MAKE_FUNCTION            4 (annotations)
            174 STORE_NAME              16 (register_cleanup_callback)

186         176 LOAD_CONST               4 ('call_uuid')
            178 LOAD_NAME                6 (str)
            180 BUILD_TUPLE              2
            182 LOAD_CONST              18 (<code object cleanup_call at 0x000001CAC40E8690, file "app\services\call_session_manager.py", line 186>)
            184 MAKE_FUNCTION            4 (annotations)
            186 STORE_NAME              17 (cleanup_call)
            188 LOAD_CLOSURE             0 (__class__)
            190 COPY                     1
            192 STORE_NAME              18 (__classcell__)
            194 RETURN_VALUE

Disassembly of <code object __new__ at 0x000001CAC3DF10B0, file "app\services\call_session_manager.py", line 12>:
              0 COPY_FREE_VARS           1

 12           2 RESUME                   0

 13           4 LOAD_FAST                0 (cls)
              6 LOAD_ATTR                0 (_instance)
             26 POP_JUMP_IF_TRUE        54 (to 136)

 14          28 LOAD_GLOBAL              3 (NULL + super)
             38 LOAD_GLOBAL              4 (CallSessionManager)
             48 LOAD_FAST                0 (cls)
             50 LOAD_SUPER_ATTR         14 (__new__)
             54 LOAD_FAST                0 (cls)
             56 BUILD_LIST               1
             58 LOAD_FAST                1 (args)
             60 LIST_EXTEND              1
             62 CALL_INTRINSIC_1         6 (INTRINSIC_LIST_TO_TUPLE)
             64 BUILD_MAP                0
             66 LOAD_FAST                2 (kwargs)
             68 DICT_MERGE               1
             70 CALL_FUNCTION_EX         1
             72 LOAD_FAST                0 (cls)
             74 STORE_ATTR               0 (_instance)

 15          84 LOAD_FAST                0 (cls)
             86 LOAD_ATTR                0 (_instance)
            106 LOAD_ATTR                9 (NULL|self + _init)
            126 CALL                     0
            134 POP_TOP

 16     >>  136 LOAD_FAST                0 (cls)
            138 LOAD_ATTR                0 (_instance)
            158 RETURN_VALUE

Disassembly of <code object _init at 0x000001CAC419BBB0, file "app\services\call_session_manager.py", line 18>:
 18           0 RESUME                   0

 20           2 BUILD_MAP                0
              4 LOAD_FAST                0 (self)
              6 STORE_ATTR               0 (active_calls)

 22          16 BUILD_MAP                0
             18 LOAD_FAST                0 (self)
             20 STORE_ATTR               1 (cleanup_callbacks)
             30 RETURN_CONST             0 (None)

Disassembly of <code object register_inbound_asterisk_call at 0x000001CAC3DED6F0, file "app\services\call_session_manager.py", line 24>:
 24           0 RESUME                   0

 36           2 LOAD_GLOBAL              0 (logger)
             12 LOAD_ATTR                3 (NULL|self + info)
             32 LOAD_CONST               1 ('[CallSessionManager] Registering inbound call ')
             34 LOAD_FAST                1 (call_uuid)
             36 FORMAT_VALUE             0
             38 LOAD_CONST               2 (' for agent ')
             40 LOAD_FAST                5 (agent_id)
             42 FORMAT_VALUE             0
             44 BUILD_STRING             4
             46 CALL                     1
             54 POP_TOP

 38          56 LOAD_FAST                1 (call_uuid)

 39          58 LOAD_FAST                2 (caller_id)

 40          60 LOAD_FAST                3 (dialed_number)

 41          62 LOAD_FAST                4 (workspace_id)

 42          64 LOAD_FAST                5 (agent_id)

 43          66 LOAD_FAST                6 (phone_number_id)

 44          68 LOAD_CONST               3 ('asterisk')

 45          70 LOAD_CONST               4 ('inbound')

 46          72 LOAD_CONST               5 ('created')

 47          74 LOAD_GLOBAL              5 (NULL + datetime)
             84 LOAD_ATTR                6 (now)
            104 LOAD_GLOBAL              8 (timezone)
            114 LOAD_ATTR               10 (utc)
            134 CALL                     1
            142 LOAD_ATTR               13 (NULL|self + isoformat)
            162 CALL                     0

 48         170 LOAD_CONST               6 (None)

 49         172 LOAD_CONST               6 (None)

 50         174 BUILD_MAP                0

 51         176 LOAD_CONST               7 (0)

 37         178 LOAD_CONST               8 (('call_uuid', 'caller_id', 'dialed_number', 'workspace_id', 'agent_id', 'phone_number_id', 'provider', 'direction', 'status', 'created_at', 'started_at', 'ended_at', 'agent_config', 'cost_cents'))
            180 BUILD_CONST_KEY_MAP     14
            182 STORE_FAST               7 (context)

 53         184 LOAD_FAST                7 (context)
            186 LOAD_FAST                0 (self)
            188 LOAD_ATTR               14 (active_calls)
            208 LOAD_FAST                1 (call_uuid)
            210 STORE_SUBSCR

 54         214 LOAD_FAST                7 (context)
            216 RETURN_VALUE

Disassembly of <code object get_call_context at 0x000001CAC40EFDB0, file "app\services\call_session_manager.py", line 56>:
              0 MAKE_CELL                1 (call_uuid)
              2 MAKE_CELL               11 (agent_id)
              4 MAKE_CELL               12 (db)

 56           6 RETURN_GENERATOR
              8 POP_TOP
             10 RESUME                   0

 60          12 LOAD_FAST                0 (self)
             14 LOAD_ATTR                0 (active_calls)
             34 LOAD_ATTR                3 (NULL|self + get)
             54 LOAD_DEREF               1 (call_uuid)
             56 CALL                     1
             64 STORE_FAST               2 (context)

 61          66 LOAD_FAST                2 (context)
             68 POP_JUMP_IF_TRUE       218 (to 506)

 63          70 LOAD_GLOBAL              5 (NULL + get_supabase_client)
             80 CALL                     0
             88 STORE_DEREF             12 (db)

 64          90 LOAD_CLOSURE             1 (call_uuid)
             92 LOAD_CLOSURE            12 (db)
             94 BUILD_TUPLE              2
             96 LOAD_CONST               1 (<code object _query at 0x000001CAC3E78DF0, file "app\services\call_session_manager.py", line 64>)
             98 MAKE_FUNCTION            8 (closure)
            100 STORE_FAST               3 (_query)

 67         102 NOP

 68         104 LOAD_GLOBAL              7 (NULL + asyncio)
            114 LOAD_ATTR                8 (to_thread)
            134 LOAD_FAST                3 (_query)
            136 CALL                     1
            144 GET_AWAITABLE            0
            146 LOAD_CONST               2 (None)
        >>  148 SEND                     3 (to 158)
            152 YIELD_VALUE              3
            154 RESUME                   3
            156 JUMP_BACKWARD_NO_INTERRUPT     5 (to 148)
        >>  158 END_SEND
            160 STORE_FAST               4 (res)

 69         162 LOAD_FAST                4 (res)
            164 LOAD_ATTR               10 (data)
            184 POP_JUMP_IF_FALSE      160 (to 506)

 70         186 LOAD_FAST                4 (res)
            188 LOAD_ATTR               10 (data)
            208 LOAD_CONST               3 (0)
            210 BINARY_SUBSCR
            214 STORE_FAST               5 (row)

 71         216 LOAD_FAST                0 (self)
            218 LOAD_ATTR               13 (NULL|self + register_inbound_asterisk_call)

 72         238 LOAD_DEREF               1 (call_uuid)

 73         240 LOAD_FAST                5 (row)
            242 LOAD_ATTR                3 (NULL|self + get)
            262 LOAD_CONST               4 ('caller_id')
            264 CALL                     1
            272 COPY                     1
            274 POP_JUMP_IF_TRUE        21 (to 318)
            276 POP_TOP
            278 LOAD_FAST                5 (row)
            280 LOAD_ATTR                3 (NULL|self + get)
            300 LOAD_CONST               5 ('caller_phone_number')
            302 CALL                     1
            310 COPY                     1
            312 POP_JUMP_IF_TRUE         2 (to 318)
            314 POP_TOP
            316 LOAD_CONST               6 ('')

 74     >>  318 LOAD_FAST                5 (row)
            320 LOAD_ATTR                3 (NULL|self + get)
            340 LOAD_CONST               7 ('dialed_number')
            342 CALL                     1
            350 COPY                     1
            352 POP_JUMP_IF_TRUE         2 (to 358)
            354 POP_TOP
            356 LOAD_CONST               6 ('')

 75     >>  358 LOAD_FAST                5 (row)
            360 LOAD_ATTR                3 (NULL|self + get)
            380 LOAD_CONST               8 ('workspace_id')
            382 CALL                     1

 76         390 LOAD_FAST                5 (row)
            392 LOAD_ATTR                3 (NULL|self + get)
            412 LOAD_CONST               9 ('agent_id')
            414 CALL                     1

 77         422 LOAD_FAST                5 (row)
            424 LOAD_ATTR                3 (NULL|self + get)
            444 LOAD_CONST              10 ('phone_number_id')
            446 CALL                     1

 71         454 KW_NAMES                11 (('call_uuid', 'caller_id', 'dialed_number', 'workspace_id', 'agent_id', 'phone_number_id'))
            456 CALL                     6
            464 STORE_FAST               2 (context)

 79         466 LOAD_FAST                5 (row)
            468 LOAD_ATTR                3 (NULL|self + get)
            488 LOAD_CONST              12 ('status')
            490 CALL                     1
            498 LOAD_FAST                2 (context)
            500 LOAD_CONST              12 ('status')
            502 STORE_SUBSCR

 84     >>  506 LOAD_FAST                2 (context)
            508 POP_JUMP_IF_TRUE         1 (to 512)

 85         510 RETURN_CONST             2 (None)

 88     >>  512 LOAD_FAST                2 (context)
            514 LOAD_ATTR                3 (NULL|self + get)
            534 LOAD_CONST              15 ('agent_config')
            536 CALL                     1
            544 EXTENDED_ARG             1
            546 POP_JUMP_IF_TRUE       283 (to 1114)

 89         548 LOAD_GLOBAL              5 (NULL + get_supabase_client)
            558 CALL                     0
            566 STORE_DEREF             12 (db)

 90         568 LOAD_FAST                2 (context)
            570 LOAD_CONST               9 ('agent_id')
            572 BINARY_SUBSCR
            576 STORE_DEREF             11 (agent_id)

 92         578 LOAD_CLOSURE            11 (agent_id)
            580 LOAD_CLOSURE            12 (db)
            582 BUILD_TUPLE              2
            584 LOAD_CONST              16 (<code object _get_agent at 0x000001CAC3E78A30, file "app\services\call_session_manager.py", line 92>)
            586 MAKE_FUNCTION            8 (closure)
            588 STORE_FAST               7 (_get_agent)

 95         590 NOP

 96         592 LOAD_GLOBAL              7 (NULL + asyncio)
            602 LOAD_ATTR                8 (to_thread)
            622 LOAD_FAST                7 (_get_agent)
            624 CALL                     1
            632 GET_AWAITABLE            0
            634 LOAD_CONST               2 (None)
        >>  636 SEND                     3 (to 646)
            640 YIELD_VALUE              3
            642 RESUME                   3
            644 JUMP_BACKWARD_NO_INTERRUPT     5 (to 636)
        >>  646 END_SEND
            648 STORE_FAST               8 (agent_res)

 97         650 LOAD_FAST                8 (agent_res)
            652 LOAD_ATTR               10 (data)
            672 POP_JUMP_IF_FALSE      218 (to 1110)

 98         674 LOAD_FAST                8 (agent_res)
            676 LOAD_ATTR               10 (data)
            696 LOAD_CONST               3 (0)
            698 BINARY_SUBSCR
            702 STORE_FAST               9 (agent)

 99         704 LOAD_FAST                9 (agent)
            706 LOAD_ATTR                3 (NULL|self + get)
            726 LOAD_CONST              17 ('kb_metadata')
            728 CALL                     1
            736 COPY                     1
            738 POP_JUMP_IF_TRUE         2 (to 744)
            740 POP_TOP
            742 BUILD_MAP                0
        >>  744 STORE_FAST              10 (kb_meta)

101         746 LOAD_FAST                9 (agent)
            748 LOAD_ATTR                3 (NULL|self + get)
            768 LOAD_CONST              18 ('name')
            770 CALL                     1

102         778 LOAD_FAST                9 (agent)
            780 LOAD_ATTR                3 (NULL|self + get)
            800 LOAD_CONST              19 ('model')
            802 CALL                     1

103         810 LOAD_FAST                9 (agent)
            812 LOAD_ATTR                3 (NULL|self + get)
            832 LOAD_CONST              20 ('language')
            834 CALL                     1
            842 COPY                     1
            844 POP_JUMP_IF_TRUE         2 (to 850)
            846 POP_TOP
            848 LOAD_CONST              21 ('hi-IN')

104     >>  850 LOAD_FAST                9 (agent)
            852 LOAD_ATTR                3 (NULL|self + get)
            872 LOAD_CONST              22 ('voice_id')
            874 CALL                     1
            882 COPY                     1
            884 POP_JUMP_IF_TRUE         2 (to 890)
            886 POP_TOP
            888 LOAD_CONST              23 ('aura-asteria-en')

105     >>  890 LOAD_FAST               10 (kb_meta)
            892 LOAD_ATTR                3 (NULL|self + get)
            912 LOAD_CONST              24 ('tts_provider')
            914 CALL                     1
            922 COPY                     1
            924 POP_JUMP_IF_TRUE         2 (to 930)
            926 POP_TOP
            928 LOAD_CONST              25 ('deepgram')

106     >>  930 LOAD_FAST                9 (agent)
            932 LOAD_ATTR                3 (NULL|self + get)
            952 LOAD_CONST              26 ('system_prompt')
            954 CALL                     1
            962 COPY                     1
            964 POP_JUMP_IF_TRUE         2 (to 970)
            966 POP_TOP
            968 LOAD_CONST               6 ('')

107     >>  970 LOAD_FAST                9 (agent)
            972 LOAD_ATTR                3 (NULL|self + get)
            992 LOAD_CONST              27 ('knowledge_base')
            994 CALL                     1
           1002 COPY                     1
           1004 POP_JUMP_IF_TRUE         2 (to 1010)
           1006 POP_TOP
           1008 LOAD_CONST               6 ('')

108     >> 1010 LOAD_FAST               10 (kb_meta)
           1012 LOAD_ATTR                3 (NULL|self + get)
           1032 LOAD_CONST              28 ('voice_gender')
           1034 CALL                     1
           1042 COPY                     1
           1044 POP_JUMP_IF_TRUE         2 (to 1050)
           1046 POP_TOP
           1048 LOAD_CONST              29 ('female')

100     >> 1050 LOAD_CONST              30 (('name', 'model', 'language', 'voice_id', 'tts_provider', 'system_prompt', 'knowledge_base', 'voice_gender'))
           1052 BUILD_CONST_KEY_MAP      8
           1054 LOAD_FAST                2 (context)
           1056 LOAD_CONST              15 ('agent_config')
           1058 STORE_SUBSCR

110        1062 LOAD_GLOBAL             16 (logger)
           1072 LOAD_ATTR               21 (NULL|self + info)
           1092 LOAD_CONST              31 ('[CallSessionManager] Loaded agent config for call ')
           1094 LOAD_DEREF               1 (call_uuid)
           1096 FORMAT_VALUE             0
           1098 BUILD_STRING             2
           1100 CALL                     1
           1108 POP_TOP

114     >> 1110 LOAD_FAST                2 (context)
           1112 RETURN_VALUE
        >> 1114 LOAD_FAST                2 (context)
           1116 RETURN_VALUE

 68     >> 1118 CLEANUP_THROW
           1120 EXTENDED_ARG             1
           1122 JUMP_BACKWARD          483 (to 158)
        >> 1124 PUSH_EXC_INFO

 80        1126 LOAD_GLOBAL             14 (Exception)
           1136 CHECK_EXC_MATCH
           1138 POP_JUMP_IF_FALSE       37 (to 1214)
           1140 STORE_FAST               6 (e)

 81        1142 LOAD_GLOBAL             16 (logger)
           1152 LOAD_ATTR               19 (NULL|self + error)
           1172 LOAD_CONST              13 ('[CallSessionManager] DB recovery lookup failed for ')
           1174 LOAD_DEREF               1 (call_uuid)
           1176 FORMAT_VALUE             0
           1178 LOAD_CONST              14 (': ')
           1180 LOAD_FAST                6 (e)
           1182 FORMAT_VALUE             0
           1184 BUILD_STRING             4
           1186 CALL                     1
           1194 POP_TOP

 82        1196 POP_EXCEPT
           1198 LOAD_CONST               2 (None)
           1200 STORE_FAST               6 (e)
           1202 DELETE_FAST              6 (e)
           1204 RETURN_CONST             2 (None)
        >> 1206 LOAD_CONST               2 (None)
           1208 STORE_FAST               6 (e)
           1210 DELETE_FAST              6 (e)
           1212 RERAISE                  1

 80     >> 1214 RERAISE                  0
        >> 1216 COPY                     3
           1218 POP_EXCEPT
           1220 RERAISE                  1

 96     >> 1222 CLEANUP_THROW
           1224 EXTENDED_ARG             1
           1226 JUMP_BACKWARD          291 (to 646)
        >> 1228 PUSH_EXC_INFO

111        1230 LOAD_GLOBAL             14 (Exception)
           1240 CHECK_EXC_MATCH
           1242 POP_JUMP_IF_FALSE       38 (to 1320)
           1244 STORE_FAST               6 (e)

112        1246 LOAD_GLOBAL             16 (logger)
           1256 LOAD_ATTR               19 (NULL|self + error)
           1276 LOAD_CONST              32 ('[CallSessionManager] Failed to load agent details for call ')
           1278 LOAD_DEREF               1 (call_uuid)
           1280 FORMAT_VALUE             0
           1282 LOAD_CONST              14 (': ')
           1284 LOAD_FAST                6 (e)
           1286 FORMAT_VALUE             0
           1288 BUILD_STRING             4
           1290 CALL                     1
           1298 POP_TOP
           1300 POP_EXCEPT
           1302 LOAD_CONST               2 (None)
           1304 STORE_FAST               6 (e)
           1306 DELETE_FAST              6 (e)

114        1308 LOAD_FAST                2 (context)
           1310 RETURN_VALUE
        >> 1312 LOAD_CONST               2 (None)
           1314 STORE_FAST               6 (e)
           1316 DELETE_FAST              6 (e)
           1318 RERAISE                  1

111     >> 1320 RERAISE                  0
        >> 1322 COPY                     3
           1324 POP_EXCEPT
           1326 RERAISE                  1
        >> 1328 CALL_INTRINSIC_1         3 (INTRINSIC_STOPITERATION_ERROR)
           1330 RERAISE                  1
ExceptionTable:
  10 to 100 -> 1328 [0] lasti
  104 to 150 -> 1124 [0]
  152 to 152 -> 1118 [2]
  154 to 504 -> 1124 [0]
  506 to 588 -> 1328 [0] lasti
  592 to 638 -> 1228 [0]
  640 to 640 -> 1222 [2]
  642 to 1108 -> 1228 [0]
  1110 to 1116 -> 1328 [0] lasti
  1118 to 1118 -> 1124 [0]
  1124 to 1140 -> 1216 [1] lasti
  1142 to 1194 -> 1206 [1] lasti
  1196 to 1204 -> 1328 [0] lasti
  1206 to 1214 -> 1216 [1] lasti
  1216 to 1220 -> 1328 [0] lasti
  1222 to 1222 -> 1228 [0]
  1228 to 1244 -> 1322 [1] lasti
  1246 to 1298 -> 1312 [1] lasti
  1300 to 1310 -> 1328 [0] lasti
  1312 to 1320 -> 1322 [1] lasti
  1322 to 1326 -> 1328 [0] lasti

Disassembly of <code object _query at 0x000001CAC3E78DF0, file "app\services\call_session_manager.py", line 64>:
              0 COPY_FREE_VARS           2

 64           2 RESUME                   0

 65           4 LOAD_DEREF               1 (db)
              6 LOAD_ATTR                1 (NULL|self + table)
             26 LOAD_CONST               1 ('calls')
             28 CALL                     1
             36 LOAD_ATTR                3 (NULL|self + select)
             56 LOAD_CONST               2 ('*')
             58 CALL                     1
             66 LOAD_ATTR                5 (NULL|self + eq)
             86 LOAD_CONST               3 ('call_uuid')
             88 LOAD_DEREF               0 (call_uuid)
             90 CALL                     2
             98 LOAD_ATTR                7 (NULL|self + execute)
            118 CALL                     0
            126 RETURN_VALUE

Disassembly of <code object _get_agent at 0x000001CAC3E78A30, file "app\services\call_session_manager.py", line 92>:
              0 COPY_FREE_VARS           2

 92           2 RESUME                   0

 93           4 LOAD_DEREF               1 (db)
              6 LOAD_ATTR                1 (NULL|self + table)
             26 LOAD_CONST               1 ('agents')
             28 CALL                     1
             36 LOAD_ATTR                3 (NULL|self + select)
             56 LOAD_CONST               2 ('*')
             58 CALL                     1
             66 LOAD_ATTR                5 (NULL|self + eq)
             86 LOAD_CONST               3 ('id')
             88 LOAD_DEREF               0 (agent_id)
             90 CALL                     2
             98 LOAD_ATTR                7 (NULL|self + execute)
            118 CALL                     0
            126 RETURN_VALUE

Disassembly of <code object start_audio_session at 0x000001CAC3C38AF0, file "app\services\call_session_manager.py", line 116>:
              0 MAKE_CELL                1 (call_uuid)
              2 MAKE_CELL                3 (context)
              4 MAKE_CELL                4 (db)

116           6 RESUME                   0

120           8 LOAD_FAST                0 (self)
             10 LOAD_ATTR                0 (active_calls)
             30 LOAD_ATTR                3 (NULL|self + get)
             50 LOAD_DEREF               1 (call_uuid)
             52 CALL                     1
             60 STORE_DEREF              3 (context)

121          62 LOAD_DEREF               3 (context)
             64 POP_JUMP_IF_TRUE         1 (to 68)

122          66 RETURN_CONST             1 (False)

123     >>   68 LOAD_CONST               2 ('in_progress')
             70 LOAD_DEREF               3 (context)
             72 LOAD_CONST               3 ('status')
             74 STORE_SUBSCR

124          78 LOAD_GLOBAL              5 (NULL + datetime)
             88 LOAD_ATTR                6 (now)
            108 LOAD_GLOBAL              8 (timezone)
            118 LOAD_ATTR               10 (utc)
            138 CALL                     1
            146 LOAD_ATTR               13 (NULL|self + isoformat)
            166 CALL                     0
            174 LOAD_DEREF               3 (context)
            176 LOAD_CONST               4 ('started_at')
            178 STORE_SUBSCR

125         182 LOAD_GLOBAL             14 (logger)
            192 LOAD_ATTR               17 (NULL|self + info)
            212 LOAD_CONST               5 ('[CallSessionManager] Audio session started for ')
            214 LOAD_DEREF               1 (call_uuid)
            216 FORMAT_VALUE             0
            218 BUILD_STRING             2
            220 CALL                     1
            228 POP_TOP

128         230 LOAD_GLOBAL             19 (NULL + get_supabase_client)
            240 CALL                     0
            248 STORE_DEREF              4 (db)

129         250 LOAD_CLOSURE             1 (call_uuid)
            252 LOAD_CLOSURE             3 (context)
            254 LOAD_CLOSURE             4 (db)
            256 BUILD_TUPLE              3
            258 LOAD_CONST               6 (<code object _update at 0x000001CAC3E50E30, file "app\services\call_session_manager.py", line 129>)
            260 MAKE_FUNCTION            8 (closure)
            262 STORE_FAST               2 (_update)

138         264 LOAD_GLOBAL             21 (NULL + asyncio)
            274 LOAD_ATTR               22 (create_task)
            294 LOAD_GLOBAL             21 (NULL + asyncio)
            304 LOAD_ATTR               24 (to_thread)
            324 LOAD_FAST                2 (_update)
            326 CALL                     1
            334 CALL                     1
            342 POP_TOP

139         344 RETURN_CONST             7 (True)

Disassembly of <code object _update at 0x000001CAC3E50E30, file "app\services\call_session_manager.py", line 129>:
              0 COPY_FREE_VARS           3

129           2 RESUME                   0

130           4 NOP

131           6 LOAD_DEREF               3 (db)
              8 LOAD_ATTR                1 (NULL|self + table)
             28 LOAD_CONST               1 ('calls')
             30 CALL                     1
             38 LOAD_ATTR                3 (NULL|self + update)

132          58 LOAD_CONST               2 ('in_progress')

133          60 LOAD_DEREF               2 (context)
             62 LOAD_CONST               3 ('started_at')
             64 BINARY_SUBSCR

131          68 LOAD_CONST               4 (('status', 'started_at'))
             70 BUILD_CONST_KEY_MAP      2
             72 CALL                     1

134          80 LOAD_ATTR                5 (NULL|self + eq)
            100 LOAD_CONST               5 ('call_uuid')
            102 LOAD_DEREF               1 (call_uuid)
            104 CALL                     2
            112 LOAD_ATTR                7 (NULL|self + execute)
            132 CALL                     0
            140 POP_TOP
            142 RETURN_CONST             0 (None)
        >>  144 PUSH_EXC_INFO

135         146 LOAD_GLOBAL              8 (Exception)
            156 CHECK_EXC_MATCH
            158 POP_JUMP_IF_FALSE       37 (to 234)
            160 STORE_FAST               0 (e)

136         162 LOAD_GLOBAL             10 (logger)
            172 LOAD_ATTR               13 (NULL|self + error)
            192 LOAD_CONST               6 ('[CallSessionManager] DB status update error for ')
            194 LOAD_DEREF               1 (call_uuid)
            196 FORMAT_VALUE             0
            198 LOAD_CONST               7 (': ')
            200 LOAD_FAST                0 (e)
            202 FORMAT_VALUE             0
            204 BUILD_STRING             4
            206 CALL                     1
            214 POP_TOP
            216 POP_EXCEPT
            218 LOAD_CONST               0 (None)
            220 STORE_FAST               0 (e)
            222 DELETE_FAST              0 (e)
            224 RETURN_CONST             0 (None)
        >>  226 LOAD_CONST               0 (None)
            228 STORE_FAST               0 (e)
            230 DELETE_FAST              0 (e)
            232 RERAISE                  1

135     >>  234 RERAISE                  0
        >>  236 COPY                     3
            238 POP_EXCEPT
            240 RERAISE                  1
ExceptionTable:
  6 to 140 -> 144 [0]
  144 to 160 -> 236 [1] lasti
  162 to 214 -> 226 [1] lasti
  226 to 234 -> 236 [1] lasti

Disassembly of <code object end_call at 0x000001CAC3C3A830, file "app\services\call_session_manager.py", line 141>:
              0 MAKE_CELL                1 (call_uuid)
              2 MAKE_CELL                2 (reason)
              4 MAKE_CELL                7 (context)
              6 MAKE_CELL                8 (db)
              8 MAKE_CELL                9 (duration)

141          10 RESUME                   0

145          12 LOAD_FAST                0 (self)
             14 LOAD_ATTR                0 (active_calls)
             34 LOAD_ATTR                3 (NULL|self + get)
             54 LOAD_DEREF               1 (call_uuid)
             56 CALL                     1
             64 STORE_DEREF              7 (context)

146          66 LOAD_DEREF               7 (context)
             68 POP_JUMP_IF_TRUE         1 (to 72)

147          70 RETURN_CONST             1 (False)

149     >>   72 LOAD_CONST               2 ('completed')
             74 LOAD_DEREF               7 (context)
             76 LOAD_CONST               3 ('status')
             78 STORE_SUBSCR

150          82 LOAD_GLOBAL              5 (NULL + datetime)
             92 LOAD_ATTR                6 (now)
            112 LOAD_GLOBAL              8 (timezone)
            122 LOAD_ATTR               10 (utc)
            142 CALL                     1
            150 LOAD_ATTR               13 (NULL|self + isoformat)
            170 CALL                     0
            178 LOAD_DEREF               7 (context)
            180 LOAD_CONST               4 ('ended_at')
            182 STORE_SUBSCR

151         186 LOAD_DEREF               2 (reason)
            188 LOAD_DEREF               7 (context)
            190 LOAD_CONST               5 ('end_reason')
            192 STORE_SUBSCR

154         196 LOAD_CONST               6 (0)
            198 STORE_DEREF              9 (duration)

155         200 LOAD_DEREF               7 (context)
            202 LOAD_ATTR                3 (NULL|self + get)
            222 LOAD_CONST               7 ('started_at')
            224 CALL                     1
            232 POP_JUMP_IF_FALSE      109 (to 452)

156         234 NOP

157         236 LOAD_GLOBAL              5 (NULL + datetime)
            246 LOAD_ATTR               14 (fromisoformat)
            266 LOAD_DEREF               7 (context)
            268 LOAD_CONST               7 ('started_at')
            270 BINARY_SUBSCR
            274 LOAD_ATTR               17 (NULL|self + replace)
            294 LOAD_CONST               8 ('Z')
            296 LOAD_CONST               9 ('+00:00')
            298 CALL                     2
            306 CALL                     1
            314 STORE_FAST               3 (start_dt)

158         316 LOAD_GLOBAL              5 (NULL + datetime)
            326 LOAD_ATTR               14 (fromisoformat)
            346 LOAD_DEREF               7 (context)
            348 LOAD_CONST               4 ('ended_at')
            350 BINARY_SUBSCR
            354 LOAD_ATTR               17 (NULL|self + replace)
            374 LOAD_CONST               8 ('Z')
            376 LOAD_CONST               9 ('+00:00')
            378 CALL                     2
            386 CALL                     1
            394 STORE_FAST               4 (end_dt)

159         396 LOAD_GLOBAL             19 (NULL + int)
            406 LOAD_FAST                4 (end_dt)
            408 LOAD_FAST                3 (start_dt)
            410 BINARY_OP               10 (-)
            414 LOAD_ATTR               21 (NULL|self + total_seconds)
            434 CALL                     0
            442 CALL                     1
            450 STORE_DEREF              9 (duration)

162     >>  452 LOAD_DEREF               9 (duration)
            454 LOAD_DEREF               7 (context)
            456 LOAD_CONST              13 ('duration_seconds')
            458 STORE_SUBSCR

164         462 LOAD_GLOBAL             24 (logger)
            472 LOAD_ATTR               29 (NULL|self + info)
            492 LOAD_CONST              14 ('[CallSessionManager] Call ')
            494 LOAD_DEREF               1 (call_uuid)
            496 FORMAT_VALUE             0
            498 LOAD_CONST              15 (' ended. Reason: ')
            500 LOAD_DEREF               2 (reason)
            502 FORMAT_VALUE             0
            504 LOAD_CONST              16 (', Duration: ')
            506 LOAD_DEREF               9 (duration)
            508 FORMAT_VALUE             0
            510 LOAD_CONST              17 ('s')
            512 BUILD_STRING             7
            514 CALL                     1
            522 POP_TOP

167         524 LOAD_GLOBAL             31 (NULL + get_supabase_client)
            534 CALL                     0
            542 STORE_DEREF              8 (db)

168         544 LOAD_CLOSURE             1 (call_uuid)
            546 LOAD_CLOSURE             7 (context)
            548 LOAD_CLOSURE             8 (db)
            550 LOAD_CLOSURE             9 (duration)
            552 LOAD_CLOSURE             2 (reason)
            554 BUILD_TUPLE              5
            556 LOAD_CONST              18 (<code object _update at 0x000001CAC3E52870, file "app\services\call_session_manager.py", line 168>)
            558 MAKE_FUNCTION            8 (closure)
            560 STORE_FAST               6 (_update)

180         562 LOAD_GLOBAL             33 (NULL + asyncio)
            572 LOAD_ATTR               34 (create_task)
            592 LOAD_GLOBAL             33 (NULL + asyncio)
            602 LOAD_ATTR               36 (to_thread)
            622 LOAD_FAST                6 (_update)
            624 CALL                     1
            632 CALL                     1
            640 POP_TOP

181         642 RETURN_CONST            19 (True)
        >>  644 PUSH_EXC_INFO

160         646 LOAD_GLOBAL             22 (Exception)
            656 CHECK_EXC_MATCH
            658 POP_JUMP_IF_FALSE       37 (to 734)
            660 STORE_FAST               5 (e)

161         662 LOAD_GLOBAL             24 (logger)
            672 LOAD_ATTR               27 (NULL|self + error)
            692 LOAD_CONST              10 ('[CallSessionManager] Error calculating duration for ')
            694 LOAD_DEREF               1 (call_uuid)
            696 FORMAT_VALUE             0
            698 LOAD_CONST              11 (': ')
            700 LOAD_FAST                5 (e)
            702 FORMAT_VALUE             0
            704 BUILD_STRING             4
            706 CALL                     1
            714 POP_TOP
            716 POP_EXCEPT
            718 LOAD_CONST              12 (None)
            720 STORE_FAST               5 (e)
            722 DELETE_FAST              5 (e)
            724 JUMP_BACKWARD          137 (to 452)
        >>  726 LOAD_CONST              12 (None)
            728 STORE_FAST               5 (e)
            730 DELETE_FAST              5 (e)
            732 RERAISE                  1

160     >>  734 RERAISE                  0
        >>  736 COPY                     3
            738 POP_EXCEPT
            740 RERAISE                  1
ExceptionTable:
  236 to 450 -> 644 [0]
  644 to 660 -> 736 [1] lasti
  662 to 714 -> 726 [1] lasti
  726 to 734 -> 736 [1] lasti

Disassembly of <code object _update at 0x000001CAC3E52870, file "app\services\call_session_manager.py", line 168>:
              0 COPY_FREE_VARS           5

168           2 RESUME                   0

169           4 NOP

170           6 LOAD_DEREF               3 (db)
              8 LOAD_ATTR                1 (NULL|self + table)
             28 LOAD_CONST               1 ('calls')
             30 CALL                     1
             38 LOAD_ATTR                3 (NULL|self + update)

171          58 LOAD_CONST               2 ('completed')

172          60 LOAD_DEREF               2 (context)
             62 LOAD_CONST               3 ('ended_at')
             64 BINARY_SUBSCR

173          68 LOAD_DEREF               4 (duration)

174          70 LOAD_DEREF               5 (reason)

175          72 LOAD_DEREF               4 (duration)

170          74 LOAD_CONST               4 (('status', 'ended_at', 'duration_seconds', 'end_reason', 'actual_duration'))
             76 BUILD_CONST_KEY_MAP      5
             78 CALL                     1

176          86 LOAD_ATTR                5 (NULL|self + eq)
            106 LOAD_CONST               5 ('call_uuid')
            108 LOAD_DEREF               1 (call_uuid)
            110 CALL                     2
            118 LOAD_ATTR                7 (NULL|self + execute)
            138 CALL                     0
            146 POP_TOP
            148 RETURN_CONST             0 (None)
        >>  150 PUSH_EXC_INFO

177         152 LOAD_GLOBAL              8 (Exception)
            162 CHECK_EXC_MATCH
            164 POP_JUMP_IF_FALSE       37 (to 240)
            166 STORE_FAST               0 (e)

178         168 LOAD_GLOBAL             10 (logger)
            178 LOAD_ATTR               13 (NULL|self + error)
            198 LOAD_CONST               6 ('[CallSessionManager] DB update error on end_call ')
            200 LOAD_DEREF               1 (call_uuid)
            202 FORMAT_VALUE             0
            204 LOAD_CONST               7 (': ')
            206 LOAD_FAST                0 (e)
            208 FORMAT_VALUE             0
            210 BUILD_STRING             4
            212 CALL                     1
            220 POP_TOP
            222 POP_EXCEPT
            224 LOAD_CONST               0 (None)
            226 STORE_FAST               0 (e)
            228 DELETE_FAST              0 (e)
            230 RETURN_CONST             0 (None)
        >>  232 LOAD_CONST               0 (None)
            234 STORE_FAST               0 (e)
            236 DELETE_FAST              0 (e)
            238 RERAISE                  1

177     >>  240 RERAISE                  0
        >>  242 COPY                     3
            244 POP_EXCEPT
            246 RERAISE                  1
ExceptionTable:
  6 to 146 -> 150 [0]
  150 to 166 -> 242 [1] lasti
  168 to 220 -> 232 [1] lasti
  232 to 240 -> 242 [1] lasti

Disassembly of <code object register_cleanup_callback at 0x000001CAC42054D0, file "app\services\call_session_manager.py", line 183>:
183           0 RESUME                   0

184           2 LOAD_FAST                2 (callback)
              4 LOAD_FAST                0 (self)
              6 LOAD_ATTR                0 (cleanup_callbacks)
             26 LOAD_FAST                1 (call_uuid)
             28 STORE_SUBSCR
             32 RETURN_CONST             0 (None)

Disassembly of <code object cleanup_call at 0x000001CAC40E8690, file "app\services\call_session_manager.py", line 186>:
186           0 RESUME                   0

190           2 LOAD_GLOBAL              0 (logger)
             12 LOAD_ATTR                3 (NULL|self + info)
             32 LOAD_CONST               1 ('[CallSessionManager] Cleaning up call ')
             34 LOAD_FAST                1 (call_uuid)
             36 FORMAT_VALUE             0
             38 BUILD_STRING             2
             40 CALL                     1
             48 POP_TOP

193          50 LOAD_FAST                0 (self)
             52 LOAD_ATTR                4 (cleanup_callbacks)
             72 LOAD_ATTR                7 (NULL|self + pop)
             92 LOAD_FAST                1 (call_uuid)
             94 LOAD_CONST               2 (None)
             96 CALL                     2
            104 STORE_FAST               2 (callback)

194         106 LOAD_FAST                2 (callback)
            108 POP_JUMP_IF_FALSE        9 (to 128)

195         110 NOP

196         112 PUSH_NULL
            114 LOAD_FAST                2 (callback)
            116 LOAD_FAST                1 (call_uuid)
            118 CALL                     1
            126 POP_TOP

201     >>  128 LOAD_FAST                0 (self)
            130 LOAD_ATTR               12 (active_calls)
            150 LOAD_ATTR                7 (NULL|self + pop)
            170 LOAD_FAST                1 (call_uuid)
            172 LOAD_CONST               2 (None)
            174 CALL                     2
            182 POP_TOP

202         184 LOAD_GLOBAL              0 (logger)
            194 LOAD_ATTR                3 (NULL|self + info)
            214 LOAD_CONST               5 ('[CallSessionManager] Cleaned up in-memory call context for ')
            216 LOAD_FAST                1 (call_uuid)
            218 FORMAT_VALUE             0
            220 BUILD_STRING             2
            222 CALL                     1
            230 POP_TOP
            232 RETURN_CONST             2 (None)
        >>  234 PUSH_EXC_INFO

197         236 LOAD_GLOBAL              8 (Exception)
            246 CHECK_EXC_MATCH
            248 POP_JUMP_IF_FALSE       37 (to 324)
            250 STORE_FAST               3 (e)

198         252 LOAD_GLOBAL              0 (logger)
            262 LOAD_ATTR               11 (NULL|self + error)
            282 LOAD_CONST               3 ('[CallSessionManager] Error during cleanup callback for ')
            284 LOAD_FAST                1 (call_uuid)
            286 FORMAT_VALUE             0
            288 LOAD_CONST               4 (': ')
            290 LOAD_FAST                3 (e)
            292 FORMAT_VALUE             0
            294 BUILD_STRING             4
            296 CALL                     1
            304 POP_TOP
            306 POP_EXCEPT
            308 LOAD_CONST               2 (None)
            310 STORE_FAST               3 (e)
            312 DELETE_FAST              3 (e)
            314 JUMP_BACKWARD           94 (to 128)
        >>  316 LOAD_CONST               2 (None)
            318 STORE_FAST               3 (e)
            320 DELETE_FAST              3 (e)
            322 RERAISE                  1

197     >>  324 RERAISE                  0
        >>  326 COPY                     3
            328 POP_EXCEPT
            330 RERAISE                  1
ExceptionTable:
  112 to 126 -> 234 [0]
  234 to 250 -> 326 [1] lasti
  252 to 304 -> 316 [1] lasti
  316 to 324 -> 326 [1] lasti

  Disassembling code object: CallSessionManager at app\services\call_session_manager.py
  Constants: ('CallSessionManager', None, <code object __new__ at 0x000001CAC3DF10B0, file "app\services\call_session_manager.py", line 12>, <code object _init at 0x000001CAC419BBB0, file "app\services\call_session_manager.py", line 18>, 'call_uuid', 'caller_id', 'dialed_number', 'workspace_id', 'agent_id', 'phone_number_id', 'return', <code object register_inbound_asterisk_call at 0x000001CAC3DED6F0, file "app\services\call_session_manager.py", line 24>, <code object get_call_context at 0x000001CAC40EFDB0, file "app\services\call_session_manager.py", line 56>, <code object start_audio_session at 0x000001CAC3C38AF0, file "app\services\call_session_manager.py", line 116>, 'reason', <code object end_call at 0x000001CAC3C3A830, file "app\services\call_session_manager.py", line 141>, 'callback', <code object register_cleanup_callback at 0x000001CAC42054D0, file "app\services\call_session_manager.py", line 183>, <code object cleanup_call at 0x000001CAC40E8690, file "app\services\call_session_manager.py", line 186>, ('hangup',))
  Names: ('__name__', '__module__', '__qualname__', '_instance', '__new__', '_init', 'str', 'Dict', 'Any', 'register_inbound_asterisk_call', 'Optional', 'get_call_context', 'bool', 'start_audio_session', 'end_call', 'Callable', 'register_cleanup_callback', 'cleanup_call', '__classcell__')
  Varnames: ()
              0 MAKE_CELL                0 (__class__)

  9           2 RESUME                   0
              4 LOAD_NAME                0 (__name__)
              6 STORE_NAME               1 (__module__)
              8 LOAD_CONST               0 ('CallSessionManager')
             10 STORE_NAME               2 (__qualname__)

 10          12 LOAD_CONST               1 (None)
             14 STORE_NAME               3 (_instance)

 12          16 LOAD_CLOSURE             0 (__class__)
             18 BUILD_TUPLE              1
             20 LOAD_CONST               2 (<code object __new__ at 0x000001CAC3DF10B0, file "app\services\call_session_manager.py", line 12>)
             22 MAKE_FUNCTION            8 (closure)
             24 STORE_NAME               4 (__new__)

 18          26 LOAD_CONST               3 (<code object _init at 0x000001CAC419BBB0, file "app\services\call_session_manager.py", line 18>)
             28 MAKE_FUNCTION            0
             30 STORE_NAME               5 (_init)

 24          32 LOAD_CONST               4 ('call_uuid')

 26          34 LOAD_NAME                6 (str)

 24          36 LOAD_CONST               5 ('caller_id')

 27          38 LOAD_NAME                6 (str)

 24          40 LOAD_CONST               6 ('dialed_number')

 28          42 LOAD_NAME                6 (str)

 24          44 LOAD_CONST               7 ('workspace_id')

 29          46 LOAD_NAME                6 (str)

 24          48 LOAD_CONST               8 ('agent_id')

 30          50 LOAD_NAME                6 (str)

 24          52 LOAD_CONST               9 ('phone_number_id')

 31          54 LOAD_NAME                6 (str)

 24          56 LOAD_CONST              10 ('return')

 32          58 LOAD_NAME                7 (Dict)
             60 LOAD_NAME                6 (str)
             62 LOAD_NAME                8 (Any)
             64 BUILD_TUPLE              2
             66 BINARY_SUBSCR

 24          70 BUILD_TUPLE             14
             72 LOAD_CONST              11 (<code object register_inbound_asterisk_call at 0x000001CAC3DED6F0, file "app\services\call_session_manager.py", line 24>)
             74 MAKE_FUNCTION            4 (annotations)
             76 STORE_NAME               9 (register_inbound_asterisk_call)

 56          78 LOAD_CONST               4 ('call_uuid')
             80 LOAD_NAME                6 (str)
             82 LOAD_CONST              10 ('return')
             84 LOAD_NAME               10 (Optional)
             86 LOAD_NAME                7 (Dict)
             88 LOAD_NAME                6 (str)
             90 LOAD_NAME                8 (Any)
             92 BUILD_TUPLE              2
             94 BINARY_SUBSCR
             98 BINARY_SUBSCR
            102 BUILD_TUPLE              4
            104 LOAD_CONST              12 (<code object get_call_context at 0x000001CAC40EFDB0, file "app\services\call_session_manager.py", line 56>)
            106 MAKE_FUNCTION            4 (annotations)
            108 STORE_NAME              11 (get_call_context)

116         110 LOAD_CONST               4 ('call_uuid')
            112 LOAD_NAME                6 (str)
            114 LOAD_CONST              10 ('return')
            116 LOAD_NAME               12 (bool)
            118 BUILD_TUPLE              4
            120 LOAD_CONST              13 (<code object start_audio_session at 0x000001CAC3C38AF0, file "app\services\call_session_manager.py", line 116>)
            122 MAKE_FUNCTION            4 (annotations)
            124 STORE_NAME              13 (start_audio_session)

141         126 LOAD_CONST              19 (('hangup',))
            128 LOAD_CONST               4 ('call_uuid')
            130 LOAD_NAME                6 (str)
            132 LOAD_CONST              14 ('reason')
            134 LOAD_NAME                6 (str)
            136 LOAD_CONST              10 ('return')
            138 LOAD_NAME               12 (bool)
            140 BUILD_TUPLE              6
            142 LOAD_CONST              15 (<code object end_call at 0x000001CAC3C3A830, file "app\services\call_session_manager.py", line 141>)
            144 MAKE_FUNCTION            5 (defaults, annotations)
            146 STORE_NAME              14 (end_call)

183         148 LOAD_CONST               4 ('call_uuid')
            150 LOAD_NAME                6 (str)
            152 LOAD_CONST              16 ('callback')
            154 LOAD_NAME               15 (Callable)
            156 LOAD_NAME                6 (str)
            158 BUILD_LIST               1
            160 LOAD_CONST               1 (None)
            162 BUILD_TUPLE              2
            164 BINARY_SUBSCR
            168 BUILD_TUPLE              4
            170 LOAD_CONST              17 (<code object register_cleanup_callback at 0x000001CAC42054D0, file "app\services\call_session_manager.py", line 183>)
            172 MAKE_FUNCTION            4 (annotations)
            174 STORE_NAME              16 (register_cleanup_callback)

186         176 LOAD_CONST               4 ('call_uuid')
            178 LOAD_NAME                6 (str)
            180 BUILD_TUPLE              2
            182 LOAD_CONST              18 (<code object cleanup_call at 0x000001CAC40E8690, file "app\services\call_session_manager.py", line 186>)
            184 MAKE_FUNCTION            4 (annotations)
            186 STORE_NAME              17 (cleanup_call)
            188 LOAD_CLOSURE             0 (__class__)
            190 COPY                     1
            192 STORE_NAME              18 (__classcell__)
            194 RETURN_VALUE

Disassembly of <code object __new__ at 0x000001CAC3DF10B0, file "app\services\call_session_manager.py", line 12>:
              0 COPY_FREE_VARS           1

 12           2 RESUME                   0

 13           4 LOAD_FAST                0 (cls)
              6 LOAD_ATTR                0 (_instance)
             26 POP_JUMP_IF_TRUE        54 (to 136)

 14          28 LOAD_GLOBAL              3 (NULL + super)
             38 LOAD_GLOBAL              4 (CallSessionManager)
             48 LOAD_FAST                0 (cls)
             50 LOAD_SUPER_ATTR         14 (__new__)
             54 LOAD_FAST                0 (cls)
             56 BUILD_LIST               1
             58 LOAD_FAST                1 (args)
             60 LIST_EXTEND              1
             62 CALL_INTRINSIC_1         6 (INTRINSIC_LIST_TO_TUPLE)
             64 BUILD_MAP                0
             66 LOAD_FAST                2 (kwargs)
             68 DICT_MERGE               1
             70 CALL_FUNCTION_EX         1
             72 LOAD_FAST                0 (cls)
             74 STORE_ATTR               0 (_instance)

 15          84 LOAD_FAST                0 (cls)
             86 LOAD_ATTR                0 (_instance)
            106 LOAD_ATTR                9 (NULL|self + _init)
            126 CALL                     0
            134 POP_TOP

 16     >>  136 LOAD_FAST                0 (cls)
            138 LOAD_ATTR                0 (_instance)
            158 RETURN_VALUE

Disassembly of <code object _init at 0x000001CAC419BBB0, file "app\services\call_session_manager.py", line 18>:
 18           0 RESUME                   0

 20           2 BUILD_MAP                0
              4 LOAD_FAST                0 (self)
              6 STORE_ATTR               0 (active_calls)

 22          16 BUILD_MAP                0
             18 LOAD_FAST                0 (self)
             20 STORE_ATTR               1 (cleanup_callbacks)
             30 RETURN_CONST             0 (None)

Disassembly of <code object register_inbound_asterisk_call at 0x000001CAC3DED6F0, file "app\services\call_session_manager.py", line 24>:
 24           0 RESUME                   0

 36           2 LOAD_GLOBAL              0 (logger)
             12 LOAD_ATTR                3 (NULL|self + info)
             32 LOAD_CONST               1 ('[CallSessionManager] Registering inbound call ')
             34 LOAD_FAST                1 (call_uuid)
             36 FORMAT_VALUE             0
             38 LOAD_CONST               2 (' for agent ')
             40 LOAD_FAST                5 (agent_id)
             42 FORMAT_VALUE             0
             44 BUILD_STRING             4
             46 CALL                     1
             54 POP_TOP

 38          56 LOAD_FAST                1 (call_uuid)

 39          58 LOAD_FAST                2 (caller_id)

 40          60 LOAD_FAST                3 (dialed_number)

 41          62 LOAD_FAST                4 (workspace_id)

 42          64 LOAD_FAST                5 (agent_id)

 43          66 LOAD_FAST                6 (phone_number_id)

 44          68 LOAD_CONST               3 ('asterisk')

 45          70 LOAD_CONST               4 ('inbound')

 46          72 LOAD_CONST               5 ('created')

 47          74 LOAD_GLOBAL              5 (NULL + datetime)
             84 LOAD_ATTR                6 (now)
            104 LOAD_GLOBAL              8 (timezone)
            114 LOAD_ATTR               10 (utc)
            134 CALL                     1
            142 LOAD_ATTR               13 (NULL|self + isoformat)
            162 CALL                     0

 48         170 LOAD_CONST               6 (None)

 49         172 LOAD_CONST               6 (None)

 50         174 BUILD_MAP                0

 51         176 LOAD_CONST               7 (0)

 37         178 LOAD_CONST               8 (('call_uuid', 'caller_id', 'dialed_number', 'workspace_id', 'agent_id', 'phone_number_id', 'provider', 'direction', 'status', 'created_at', 'started_at', 'ended_at', 'agent_config', 'cost_cents'))
            180 BUILD_CONST_KEY_MAP     14
            182 STORE_FAST               7 (context)

 53         184 LOAD_FAST                7 (context)
            186 LOAD_FAST                0 (self)
            188 LOAD_ATTR               14 (active_calls)
            208 LOAD_FAST                1 (call_uuid)
            210 STORE_SUBSCR

 54         214 LOAD_FAST                7 (context)
            216 RETURN_VALUE

Disassembly of <code object get_call_context at 0x000001CAC40EFDB0, file "app\services\call_session_manager.py", line 56>:
              0 MAKE_CELL                1 (call_uuid)
              2 MAKE_CELL               11 (agent_id)
              4 MAKE_CELL               12 (db)

 56           6 RETURN_GENERATOR
              8 POP_TOP
             10 RESUME                   0

 60          12 LOAD_FAST                0 (self)
             14 LOAD_ATTR                0 (active_calls)
             34 LOAD_ATTR                3 (NULL|self + get)
             54 LOAD_DEREF               1 (call_uuid)
             56 CALL                     1
             64 STORE_FAST               2 (context)

 61          66 LOAD_FAST                2 (context)
             68 POP_JUMP_IF_TRUE       218 (to 506)

 63          70 LOAD_GLOBAL              5 (NULL + get_supabase_client)
             80 CALL                     0
             88 STORE_DEREF             12 (db)

 64          90 LOAD_CLOSURE             1 (call_uuid)
             92 LOAD_CLOSURE            12 (db)
             94 BUILD_TUPLE              2
             96 LOAD_CONST               1 (<code object _query at 0x000001CAC3E78DF0, file "app\services\call_session_manager.py", line 64>)
             98 MAKE_FUNCTION            8 (closure)
            100 STORE_FAST               3 (_query)

 67         102 NOP

 68         104 LOAD_GLOBAL              7 (NULL + asyncio)
            114 LOAD_ATTR                8 (to_thread)
            134 LOAD_FAST                3 (_query)
            136 CALL                     1
            144 GET_AWAITABLE            0
            146 LOAD_CONST               2 (None)
        >>  148 SEND                     3 (to 158)
            152 YIELD_VALUE              3
            154 RESUME                   3
            156 JUMP_BACKWARD_NO_INTERRUPT     5 (to 148)
        >>  158 END_SEND
            160 STORE_FAST               4 (res)

 69         162 LOAD_FAST                4 (res)
            164 LOAD_ATTR               10 (data)
            184 POP_JUMP_IF_FALSE      160 (to 506)

 70         186 LOAD_FAST                4 (res)
            188 LOAD_ATTR               10 (data)
            208 LOAD_CONST               3 (0)
            210 BINARY_SUBSCR
            214 STORE_FAST               5 (row)

 71         216 LOAD_FAST                0 (self)
            218 LOAD_ATTR               13 (NULL|self + register_inbound_asterisk_call)

 72         238 LOAD_DEREF               1 (call_uuid)

 73         240 LOAD_FAST                5 (row)
            242 LOAD_ATTR                3 (NULL|self + get)
            262 LOAD_CONST               4 ('caller_id')
            264 CALL                     1
            272 COPY                     1
            274 POP_JUMP_IF_TRUE        21 (to 318)
            276 POP_TOP
            278 LOAD_FAST                5 (row)
            280 LOAD_ATTR                3 (NULL|self + get)
            300 LOAD_CONST               5 ('caller_phone_number')
            302 CALL                     1
            310 COPY                     1
            312 POP_JUMP_IF_TRUE         2 (to 318)
            314 POP_TOP
            316 LOAD_CONST               6 ('')

 74     >>  318 LOAD_FAST                5 (row)
            320 LOAD_ATTR                3 (NULL|self + get)
            340 LOAD_CONST               7 ('dialed_number')
            342 CALL                     1
            350 COPY                     1
            352 POP_JUMP_IF_TRUE         2 (to 358)
            354 POP_TOP
            356 LOAD_CONST               6 ('')

 75     >>  358 LOAD_FAST                5 (row)
            360 LOAD_ATTR                3 (NULL|self + get)
            380 LOAD_CONST               8 ('workspace_id')
            382 CALL                     1

 76         390 LOAD_FAST                5 (row)
            392 LOAD_ATTR                3 (NULL|self + get)
            412 LOAD_CONST               9 ('agent_id')
            414 CALL                     1

 77         422 LOAD_FAST                5 (row)
            424 LOAD_ATTR                3 (NULL|self + get)
            444 LOAD_CONST              10 ('phone_number_id')
            446 CALL                     1

 71         454 KW_NAMES                11 (('call_uuid', 'caller_id', 'dialed_number', 'workspace_id', 'agent_id', 'phone_number_id'))
            456 CALL                     6
            464 STORE_FAST               2 (context)

 79         466 LOAD_FAST                5 (row)
            468 LOAD_ATTR                3 (NULL|self + get)
            488 LOAD_CONST              12 ('status')
            490 CALL                     1
            498 LOAD_FAST                2 (context)
            500 LOAD_CONST              12 ('status')
            502 STORE_SUBSCR

 84     >>  506 LOAD_FAST                2 (context)
            508 POP_JUMP_IF_TRUE         1 (to 512)

 85         510 RETURN_CONST             2 (None)

 88     >>  512 LOAD_FAST                2 (context)
            514 LOAD_ATTR                3 (NULL|self + get)
            534 LOAD_CONST              15 ('agent_config')
            536 CALL                     1
            544 EXTENDED_ARG             1
            546 POP_JUMP_IF_TRUE       283 (to 1114)

 89         548 LOAD_GLOBAL              5 (NULL + get_supabase_client)
            558 CALL                     0
            566 STORE_DEREF             12 (db)

 90         568 LOAD_FAST                2 (context)
            570 LOAD_CONST               9 ('agent_id')
            572 BINARY_SUBSCR
            576 STORE_DEREF             11 (agent_id)

 92         578 LOAD_CLOSURE            11 (agent_id)
            580 LOAD_CLOSURE            12 (db)
            582 BUILD_TUPLE              2
            584 LOAD_CONST              16 (<code object _get_agent at 0x000001CAC3E78A30, file "app\services\call_session_manager.py", line 92>)
            586 MAKE_FUNCTION            8 (closure)
            588 STORE_FAST               7 (_get_agent)

 95         590 NOP

 96         592 LOAD_GLOBAL              7 (NULL + asyncio)
            602 LOAD_ATTR                8 (to_thread)
            622 LOAD_FAST                7 (_get_agent)
            624 CALL                     1
            632 GET_AWAITABLE            0
            634 LOAD_CONST               2 (None)
        >>  636 SEND                     3 (to 646)
            640 YIELD_VALUE              3
            642 RESUME                   3
            644 JUMP_BACKWARD_NO_INTERRUPT     5 (to 636)
        >>  646 END_SEND
            648 STORE_FAST               8 (agent_res)

 97         650 LOAD_FAST                8 (agent_res)
            652 LOAD_ATTR               10 (data)
            672 POP_JUMP_IF_FALSE      218 (to 1110)

 98         674 LOAD_FAST                8 (agent_res)
            676 LOAD_ATTR               10 (data)
            696 LOAD_CONST               3 (0)
            698 BINARY_SUBSCR
            702 STORE_FAST               9 (agent)

 99         704 LOAD_FAST                9 (agent)
            706 LOAD_ATTR                3 (NULL|self + get)
            726 LOAD_CONST              17 ('kb_metadata')
            728 CALL                     1
            736 COPY                     1
            738 POP_JUMP_IF_TRUE         2 (to 744)
            740 POP_TOP
            742 BUILD_MAP                0
        >>  744 STORE_FAST              10 (kb_meta)

101         746 LOAD_FAST                9 (agent)
            748 LOAD_ATTR                3 (NULL|self + get)
            768 LOAD_CONST              18 ('name')
            770 CALL                     1

102         778 LOAD_FAST                9 (agent)
            780 LOAD_ATTR                3 (NULL|self + get)
            800 LOAD_CONST              19 ('model')
            802 CALL                     1

103         810 LOAD_FAST                9 (agent)
            812 LOAD_ATTR                3 (NULL|self + get)
            832 LOAD_CONST              20 ('language')
            834 CALL                     1
            842 COPY                     1
            844 POP_JUMP_IF_TRUE         2 (to 850)
            846 POP_TOP
            848 LOAD_CONST              21 ('hi-IN')

104     >>  850 LOAD_FAST                9 (agent)
            852 LOAD_ATTR                3 (NULL|self + get)
            872 LOAD_CONST              22 ('voice_id')
            874 CALL                     1
            882 COPY                     1
            884 POP_JUMP_IF_TRUE         2 (to 890)
            886 POP_TOP
            888 LOAD_CONST              23 ('aura-asteria-en')

105     >>  890 LOAD_FAST               10 (kb_meta)
            892 LOAD_ATTR                3 (NULL|self + get)
            912 LOAD_CONST              24 ('tts_provider')
            914 CALL                     1
            922 COPY                     1
            924 POP_JUMP_IF_TRUE         2 (to 930)
            926 POP_TOP
            928 LOAD_CONST              25 ('deepgram')

106     >>  930 LOAD_FAST                9 (agent)
            932 LOAD_ATTR                3 (NULL|self + get)
            952 LOAD_CONST              26 ('system_prompt')
            954 CALL                     1
            962 COPY                     1
            964 POP_JUMP_IF_TRUE         2 (to 970)
            966 POP_TOP
            968 LOAD_CONST               6 ('')

107     >>  970 LOAD_FAST                9 (agent)
            972 LOAD_ATTR                3 (NULL|self + get)
            992 LOAD_CONST              27 ('knowledge_base')
            994 CALL                     1
           1002 COPY                     1
           1004 POP_JUMP_IF_TRUE         2 (to 1010)
           1006 POP_TOP
           1008 LOAD_CONST               6 ('')

108     >> 1010 LOAD_FAST               10 (kb_meta)
           1012 LOAD_ATTR                3 (NULL|self + get)
           1032 LOAD_CONST              28 ('voice_gender')
           1034 CALL                     1
           1042 COPY                     1
           1044 POP_JUMP_IF_TRUE         2 (to 1050)
           1046 POP_TOP
           1048 LOAD_CONST              29 ('female')

100     >> 1050 LOAD_CONST              30 (('name', 'model', 'language', 'voice_id', 'tts_provider', 'system_prompt', 'knowledge_base', 'voice_gender'))
           1052 BUILD_CONST_KEY_MAP      8
           1054 LOAD_FAST                2 (context)
           1056 LOAD_CONST              15 ('agent_config')
           1058 STORE_SUBSCR

110        1062 LOAD_GLOBAL             16 (logger)
           1072 LOAD_ATTR               21 (NULL|self + info)
           1092 LOAD_CONST              31 ('[CallSessionManager] Loaded agent config for call ')
           1094 LOAD_DEREF               1 (call_uuid)
           1096 FORMAT_VALUE             0
           1098 BUILD_STRING             2
           1100 CALL                     1
           1108 POP_TOP

114     >> 1110 LOAD_FAST                2 (context)
           1112 RETURN_VALUE
        >> 1114 LOAD_FAST                2 (context)
           1116 RETURN_VALUE

 68     >> 1118 CLEANUP_THROW
           1120 EXTENDED_ARG             1
           1122 JUMP_BACKWARD          483 (to 158)
        >> 1124 PUSH_EXC_INFO

 80        1126 LOAD_GLOBAL             14 (Exception)
           1136 CHECK_EXC_MATCH
           1138 POP_JUMP_IF_FALSE       37 (to 1214)
           1140 STORE_FAST               6 (e)

 81        1142 LOAD_GLOBAL             16 (logger)
           1152 LOAD_ATTR               19 (NULL|self + error)
           1172 LOAD_CONST              13 ('[CallSessionManager] DB recovery lookup failed for ')
           1174 LOAD_DEREF               1 (call_uuid)
           1176 FORMAT_VALUE             0
           1178 LOAD_CONST              14 (': ')
           1180 LOAD_FAST                6 (e)
           1182 FORMAT_VALUE             0
           1184 BUILD_STRING             4
           1186 CALL                     1
           1194 POP_TOP

 82        1196 POP_EXCEPT
           1198 LOAD_CONST               2 (None)
           1200 STORE_FAST               6 (e)
           1202 DELETE_FAST              6 (e)
           1204 RETURN_CONST             2 (None)
        >> 1206 LOAD_CONST               2 (None)
           1208 STORE_FAST               6 (e)
           1210 DELETE_FAST              6 (e)
           1212 RERAISE                  1

 80     >> 1214 RERAISE                  0
        >> 1216 COPY                     3
           1218 POP_EXCEPT
           1220 RERAISE                  1

 96     >> 1222 CLEANUP_THROW
           1224 EXTENDED_ARG             1
           1226 JUMP_BACKWARD          291 (to 646)
        >> 1228 PUSH_EXC_INFO

111        1230 LOAD_GLOBAL             14 (Exception)
           1240 CHECK_EXC_MATCH
           1242 POP_JUMP_IF_FALSE       38 (to 1320)
           1244 STORE_FAST               6 (e)

112        1246 LOAD_GLOBAL             16 (logger)
           1256 LOAD_ATTR               19 (NULL|self + error)
           1276 LOAD_CONST              32 ('[CallSessionManager] Failed to load agent details for call ')
           1278 LOAD_DEREF               1 (call_uuid)
           1280 FORMAT_VALUE             0
           1282 LOAD_CONST              14 (': ')
           1284 LOAD_FAST                6 (e)
           1286 FORMAT_VALUE             0
           1288 BUILD_STRING             4
           1290 CALL                     1
           1298 POP_TOP
           1300 POP_EXCEPT
           1302 LOAD_CONST               2 (None)
           1304 STORE_FAST               6 (e)
           1306 DELETE_FAST              6 (e)

114        1308 LOAD_FAST                2 (context)
           1310 RETURN_VALUE
        >> 1312 LOAD_CONST               2 (None)
           1314 STORE_FAST               6 (e)
           1316 DELETE_FAST              6 (e)
           1318 RERAISE                  1

111     >> 1320 RERAISE                  0
        >> 1322 COPY                     3
           1324 POP_EXCEPT
           1326 RERAISE                  1
        >> 1328 CALL_INTRINSIC_1         3 (INTRINSIC_STOPITERATION_ERROR)
           1330 RERAISE                  1
ExceptionTable:
  10 to 100 -> 1328 [0] lasti
  104 to 150 -> 1124 [0]
  152 to 152 -> 1118 [2]
  154 to 504 -> 1124 [0]
  506 to 588 -> 1328 [0] lasti
  592 to 638 -> 1228 [0]
  640 to 640 -> 1222 [2]
  642 to 1108 -> 1228 [0]
  1110 to 1116 -> 1328 [0] lasti
  1118 to 1118 -> 1124 [0]
  1124 to 1140 -> 1216 [1] lasti
  1142 to 1194 -> 1206 [1] lasti
  1196 to 1204 -> 1328 [0] lasti
  1206 to 1214 -> 1216 [1] lasti
  1216 to 1220 -> 1328 [0] lasti
  1222 to 1222 -> 1228 [0]
  1228 to 1244 -> 1322 [1] lasti
  1246 to 1298 -> 1312 [1] lasti
  1300 to 1310 -> 1328 [0] lasti
  1312 to 1320 -> 1322 [1] lasti
  1322 to 1326 -> 1328 [0] lasti

Disassembly of <code object _query at 0x000001CAC3E78DF0, file "app\services\call_session_manager.py", line 64>:
              0 COPY_FREE_VARS           2

 64           2 RESUME                   0

 65           4 LOAD_DEREF               1 (db)
              6 LOAD_ATTR                1 (NULL|self + table)
             26 LOAD_CONST               1 ('calls')
             28 CALL                     1
             36 LOAD_ATTR                3 (NULL|self + select)
             56 LOAD_CONST               2 ('*')
             58 CALL                     1
             66 LOAD_ATTR                5 (NULL|self + eq)
             86 LOAD_CONST               3 ('call_uuid')
             88 LOAD_DEREF               0 (call_uuid)
             90 CALL                     2
             98 LOAD_ATTR                7 (NULL|self + execute)
            118 CALL                     0
            126 RETURN_VALUE

Disassembly of <code object _get_agent at 0x000001CAC3E78A30, file "app\services\call_session_manager.py", line 92>:
              0 COPY_FREE_VARS           2

 92           2 RESUME                   0

 93           4 LOAD_DEREF               1 (db)
              6 LOAD_ATTR                1 (NULL|self + table)
             26 LOAD_CONST               1 ('agents')
             28 CALL                     1
             36 LOAD_ATTR                3 (NULL|self + select)
             56 LOAD_CONST               2 ('*')
             58 CALL                     1
             66 LOAD_ATTR                5 (NULL|self + eq)
             86 LOAD_CONST               3 ('id')
             88 LOAD_DEREF               0 (agent_id)
             90 CALL                     2
             98 LOAD_ATTR                7 (NULL|self + execute)
            118 CALL                     0
            126 RETURN_VALUE

Disassembly of <code object start_audio_session at 0x000001CAC3C38AF0, file "app\services\call_session_manager.py", line 116>:
              0 MAKE_CELL                1 (call_uuid)
              2 MAKE_CELL                3 (context)
              4 MAKE_CELL                4 (db)

116           6 RESUME                   0

120           8 LOAD_FAST                0 (self)
             10 LOAD_ATTR                0 (active_calls)
             30 LOAD_ATTR                3 (NULL|self + get)
             50 LOAD_DEREF               1 (call_uuid)
             52 CALL                     1
             60 STORE_DEREF              3 (context)

121          62 LOAD_DEREF               3 (context)
             64 POP_JUMP_IF_TRUE         1 (to 68)

122          66 RETURN_CONST             1 (False)

123     >>   68 LOAD_CONST               2 ('in_progress')
             70 LOAD_DEREF               3 (context)
             72 LOAD_CONST               3 ('status')
             74 STORE_SUBSCR

124          78 LOAD_GLOBAL              5 (NULL + datetime)
             88 LOAD_ATTR                6 (now)
            108 LOAD_GLOBAL              8 (timezone)
            118 LOAD_ATTR               10 (utc)
            138 CALL                     1
            146 LOAD_ATTR               13 (NULL|self + isoformat)
            166 CALL                     0
            174 LOAD_DEREF               3 (context)
            176 LOAD_CONST               4 ('started_at')
            178 STORE_SUBSCR

125         182 LOAD_GLOBAL             14 (logger)
            192 LOAD_ATTR               17 (NULL|self + info)
            212 LOAD_CONST               5 ('[CallSessionManager] Audio session started for ')
            214 LOAD_DEREF               1 (call_uuid)
            216 FORMAT_VALUE             0
            218 BUILD_STRING             2
            220 CALL                     1
            228 POP_TOP

128         230 LOAD_GLOBAL             19 (NULL + get_supabase_client)
            240 CALL                     0
            248 STORE_DEREF              4 (db)

129         250 LOAD_CLOSURE             1 (call_uuid)
            252 LOAD_CLOSURE             3 (context)
            254 LOAD_CLOSURE             4 (db)
            256 BUILD_TUPLE              3
            258 LOAD_CONST               6 (<code object _update at 0x000001CAC3E50E30, file "app\services\call_session_manager.py", line 129>)
            260 MAKE_FUNCTION            8 (closure)
            262 STORE_FAST               2 (_update)

138         264 LOAD_GLOBAL             21 (NULL + asyncio)
            274 LOAD_ATTR               22 (create_task)
            294 LOAD_GLOBAL             21 (NULL + asyncio)
            304 LOAD_ATTR               24 (to_thread)
            324 LOAD_FAST                2 (_update)
            326 CALL                     1
            334 CALL                     1
            342 POP_TOP

139         344 RETURN_CONST             7 (True)

Disassembly of <code object _update at 0x000001CAC3E50E30, file "app\services\call_session_manager.py", line 129>:
              0 COPY_FREE_VARS           3

129           2 RESUME                   0

130           4 NOP

131           6 LOAD_DEREF               3 (db)
              8 LOAD_ATTR                1 (NULL|self + table)
             28 LOAD_CONST               1 ('calls')
             30 CALL                     1
             38 LOAD_ATTR                3 (NULL|self + update)

132          58 LOAD_CONST               2 ('in_progress')

133          60 LOAD_DEREF               2 (context)
             62 LOAD_CONST               3 ('started_at')
             64 BINARY_SUBSCR

131          68 LOAD_CONST               4 (('status', 'started_at'))
             70 BUILD_CONST_KEY_MAP      2
             72 CALL                     1

134          80 LOAD_ATTR                5 (NULL|self + eq)
            100 LOAD_CONST               5 ('call_uuid')
            102 LOAD_DEREF               1 (call_uuid)
            104 CALL                     2
            112 LOAD_ATTR                7 (NULL|self + execute)
            132 CALL                     0
            140 POP_TOP
            142 RETURN_CONST             0 (None)
        >>  144 PUSH_EXC_INFO

135         146 LOAD_GLOBAL              8 (Exception)
            156 CHECK_EXC_MATCH
            158 POP_JUMP_IF_FALSE       37 (to 234)
            160 STORE_FAST               0 (e)

136         162 LOAD_GLOBAL             10 (logger)
            172 LOAD_ATTR               13 (NULL|self + error)
            192 LOAD_CONST               6 ('[CallSessionManager] DB status update error for ')
            194 LOAD_DEREF               1 (call_uuid)
            196 FORMAT_VALUE             0
            198 LOAD_CONST               7 (': ')
            200 LOAD_FAST                0 (e)
            202 FORMAT_VALUE             0
            204 BUILD_STRING             4
            206 CALL                     1
            214 POP_TOP
            216 POP_EXCEPT
            218 LOAD_CONST               0 (None)
            220 STORE_FAST               0 (e)
            222 DELETE_FAST              0 (e)
            224 RETURN_CONST             0 (None)
        >>  226 LOAD_CONST               0 (None)
            228 STORE_FAST               0 (e)
            230 DELETE_FAST              0 (e)
            232 RERAISE                  1

135     >>  234 RERAISE                  0
        >>  236 COPY                     3
            238 POP_EXCEPT
            240 RERAISE                  1
ExceptionTable:
  6 to 140 -> 144 [0]
  144 to 160 -> 236 [1] lasti
  162 to 214 -> 226 [1] lasti
  226 to 234 -> 236 [1] lasti

Disassembly of <code object end_call at 0x000001CAC3C3A830, file "app\services\call_session_manager.py", line 141>:
              0 MAKE_CELL                1 (call_uuid)
              2 MAKE_CELL                2 (reason)
              4 MAKE_CELL                7 (context)
              6 MAKE_CELL                8 (db)
              8 MAKE_CELL                9 (duration)

141          10 RESUME                   0

145          12 LOAD_FAST                0 (self)
             14 LOAD_ATTR                0 (active_calls)
             34 LOAD_ATTR                3 (NULL|self + get)
             54 LOAD_DEREF               1 (call_uuid)
             56 CALL                     1
             64 STORE_DEREF              7 (context)

146          66 LOAD_DEREF               7 (context)
             68 POP_JUMP_IF_TRUE         1 (to 72)

147          70 RETURN_CONST             1 (False)

149     >>   72 LOAD_CONST               2 ('completed')
             74 LOAD_DEREF               7 (context)
             76 LOAD_CONST               3 ('status')
             78 STORE_SUBSCR

150          82 LOAD_GLOBAL              5 (NULL + datetime)
             92 LOAD_ATTR                6 (now)
            112 LOAD_GLOBAL              8 (timezone)
            122 LOAD_ATTR               10 (utc)
            142 CALL                     1
            150 LOAD_ATTR               13 (NULL|self + isoformat)
            170 CALL                     0
            178 LOAD_DEREF               7 (context)
            180 LOAD_CONST               4 ('ended_at')
            182 STORE_SUBSCR

151         186 LOAD_DEREF               2 (reason)
            188 LOAD_DEREF               7 (context)
            190 LOAD_CONST               5 ('end_reason')
            192 STORE_SUBSCR

154         196 LOAD_CONST               6 (0)
            198 STORE_DEREF              9 (duration)

155         200 LOAD_DEREF               7 (context)
            202 LOAD_ATTR                3 (NULL|self + get)
            222 LOAD_CONST               7 ('started_at')
            224 CALL                     1
            232 POP_JUMP_IF_FALSE      109 (to 452)

156         234 NOP

157         236 LOAD_GLOBAL              5 (NULL + datetime)
            246 LOAD_ATTR               14 (fromisoformat)
            266 LOAD_DEREF               7 (context)
            268 LOAD_CONST               7 ('started_at')
            270 BINARY_SUBSCR
            274 LOAD_ATTR               17 (NULL|self + replace)
            294 LOAD_CONST               8 ('Z')
            296 LOAD_CONST               9 ('+00:00')
            298 CALL                     2
            306 CALL                     1
            314 STORE_FAST               3 (start_dt)

158         316 LOAD_GLOBAL              5 (NULL + datetime)
            326 LOAD_ATTR               14 (fromisoformat)
            346 LOAD_DEREF               7 (context)
            348 LOAD_CONST               4 ('ended_at')
            350 BINARY_SUBSCR
            354 LOAD_ATTR               17 (NULL|self + replace)
            374 LOAD_CONST               8 ('Z')
            376 LOAD_CONST               9 ('+00:00')
            378 CALL                     2
            386 CALL                     1
            394 STORE_FAST               4 (end_dt)

159         396 LOAD_GLOBAL             19 (NULL + int)
            406 LOAD_FAST                4 (end_dt)
            408 LOAD_FAST                3 (start_dt)
            410 BINARY_OP               10 (-)
            414 LOAD_ATTR               21 (NULL|self + total_seconds)
            434 CALL                     0
            442 CALL                     1
            450 STORE_DEREF              9 (duration)

162     >>  452 LOAD_DEREF               9 (duration)
            454 LOAD_DEREF               7 (context)
            456 LOAD_CONST              13 ('duration_seconds')
            458 STORE_SUBSCR

164         462 LOAD_GLOBAL             24 (logger)
            472 LOAD_ATTR               29 (NULL|self + info)
            492 LOAD_CONST              14 ('[CallSessionManager] Call ')
            494 LOAD_DEREF               1 (call_uuid)
            496 FORMAT_VALUE             0
            498 LOAD_CONST              15 (' ended. Reason: ')
            500 LOAD_DEREF               2 (reason)
            502 FORMAT_VALUE             0
            504 LOAD_CONST              16 (', Duration: ')
            506 LOAD_DEREF               9 (duration)
            508 FORMAT_VALUE             0
            510 LOAD_CONST              17 ('s')
            512 BUILD_STRING             7
            514 CALL                     1
            522 POP_TOP

167         524 LOAD_GLOBAL             31 (NULL + get_supabase_client)
            534 CALL                     0
            542 STORE_DEREF              8 (db)

168         544 LOAD_CLOSURE             1 (call_uuid)
            546 LOAD_CLOSURE             7 (context)
            548 LOAD_CLOSURE             8 (db)
            550 LOAD_CLOSURE             9 (duration)
            552 LOAD_CLOSURE             2 (reason)
            554 BUILD_TUPLE              5
            556 LOAD_CONST              18 (<code object _update at 0x000001CAC3E52870, file "app\services\call_session_manager.py", line 168>)
            558 MAKE_FUNCTION            8 (closure)
            560 STORE_FAST               6 (_update)

180         562 LOAD_GLOBAL             33 (NULL + asyncio)
            572 LOAD_ATTR               34 (create_task)
            592 LOAD_GLOBAL             33 (NULL + asyncio)
            602 LOAD_ATTR               36 (to_thread)
            622 LOAD_FAST                6 (_update)
            624 CALL                     1
            632 CALL                     1
            640 POP_TOP

181         642 RETURN_CONST            19 (True)
        >>  644 PUSH_EXC_INFO

160         646 LOAD_GLOBAL             22 (Exception)
            656 CHECK_EXC_MATCH
            658 POP_JUMP_IF_FALSE       37 (to 734)
            660 STORE_FAST               5 (e)

161         662 LOAD_GLOBAL             24 (logger)
            672 LOAD_ATTR               27 (NULL|self + error)
            692 LOAD_CONST              10 ('[CallSessionManager] Error calculating duration for ')
            694 LOAD_DEREF               1 (call_uuid)
            696 FORMAT_VALUE             0
            698 LOAD_CONST              11 (': ')
            700 LOAD_FAST                5 (e)
            702 FORMAT_VALUE             0
            704 BUILD_STRING             4
            706 CALL                     1
            714 POP_TOP
            716 POP_EXCEPT
            718 LOAD_CONST              12 (None)
            720 STORE_FAST               5 (e)
            722 DELETE_FAST              5 (e)
            724 JUMP_BACKWARD          137 (to 452)
        >>  726 LOAD_CONST              12 (None)
            728 STORE_FAST               5 (e)
            730 DELETE_FAST              5 (e)
            732 RERAISE                  1

160     >>  734 RERAISE                  0
        >>  736 COPY                     3
            738 POP_EXCEPT
            740 RERAISE                  1
ExceptionTable:
  236 to 450 -> 644 [0]
  644 to 660 -> 736 [1] lasti
  662 to 714 -> 726 [1] lasti
  726 to 734 -> 736 [1] lasti

Disassembly of <code object _update at 0x000001CAC3E52870, file "app\services\call_session_manager.py", line 168>:
              0 COPY_FREE_VARS           5

168           2 RESUME                   0

169           4 NOP

170           6 LOAD_DEREF               3 (db)
              8 LOAD_ATTR                1 (NULL|self + table)
             28 LOAD_CONST               1 ('calls')
             30 CALL                     1
             38 LOAD_ATTR                3 (NULL|self + update)

171          58 LOAD_CONST               2 ('completed')

172          60 LOAD_DEREF               2 (context)
             62 LOAD_CONST               3 ('ended_at')
             64 BINARY_SUBSCR

173          68 LOAD_DEREF               4 (duration)

174          70 LOAD_DEREF               5 (reason)

175          72 LOAD_DEREF               4 (duration)

170          74 LOAD_CONST               4 (('status', 'ended_at', 'duration_seconds', 'end_reason', 'actual_duration'))
             76 BUILD_CONST_KEY_MAP      5
             78 CALL                     1

176          86 LOAD_ATTR                5 (NULL|self + eq)
            106 LOAD_CONST               5 ('call_uuid')
            108 LOAD_DEREF               1 (call_uuid)
            110 CALL                     2
            118 LOAD_ATTR                7 (NULL|self + execute)
            138 CALL                     0
            146 POP_TOP
            148 RETURN_CONST             0 (None)
        >>  150 PUSH_EXC_INFO

177         152 LOAD_GLOBAL              8 (Exception)
            162 CHECK_EXC_MATCH
            164 POP_JUMP_IF_FALSE       37 (to 240)
            166 STORE_FAST               0 (e)

178         168 LOAD_GLOBAL             10 (logger)
            178 LOAD_ATTR               13 (NULL|self + error)
            198 LOAD_CONST               6 ('[CallSessionManager] DB update error on end_call ')
            200 LOAD_DEREF               1 (call_uuid)
            202 FORMAT_VALUE             0
            204 LOAD_CONST               7 (': ')
            206 LOAD_FAST                0 (e)
            208 FORMAT_VALUE             0
            210 BUILD_STRING             4
            212 CALL                     1
            220 POP_TOP
            222 POP_EXCEPT
            224 LOAD_CONST               0 (None)
            226 STORE_FAST               0 (e)
            228 DELETE_FAST              0 (e)
            230 RETURN_CONST             0 (None)
        >>  232 LOAD_CONST               0 (None)
            234 STORE_FAST               0 (e)
            236 DELETE_FAST              0 (e)
            238 RERAISE                  1

177     >>  240 RERAISE                  0
        >>  242 COPY                     3
            244 POP_EXCEPT
            246 RERAISE                  1
ExceptionTable:
  6 to 146 -> 150 [0]
  150 to 166 -> 242 [1] lasti
  168 to 220 -> 232 [1] lasti
  232 to 240 -> 242 [1] lasti

Disassembly of <code object register_cleanup_callback at 0x000001CAC42054D0, file "app\services\call_session_manager.py", line 183>:
183           0 RESUME                   0

184           2 LOAD_FAST                2 (callback)
              4 LOAD_FAST                0 (self)
              6 LOAD_ATTR                0 (cleanup_callbacks)
             26 LOAD_FAST                1 (call_uuid)
             28 STORE_SUBSCR
             32 RETURN_CONST             0 (None)

Disassembly of <code object cleanup_call at 0x000001CAC40E8690, file "app\services\call_session_manager.py", line 186>:
186           0 RESUME                   0

190           2 LOAD_GLOBAL              0 (logger)
             12 LOAD_ATTR                3 (NULL|self + info)
             32 LOAD_CONST               1 ('[CallSessionManager] Cleaning up call ')
             34 LOAD_FAST                1 (call_uuid)
             36 FORMAT_VALUE             0
             38 BUILD_STRING             2
             40 CALL                     1
             48 POP_TOP

193          50 LOAD_FAST                0 (self)
             52 LOAD_ATTR                4 (cleanup_callbacks)
             72 LOAD_ATTR                7 (NULL|self + pop)
             92 LOAD_FAST                1 (call_uuid)
             94 LOAD_CONST               2 (None)
             96 CALL                     2
            104 STORE_FAST               2 (callback)

194         106 LOAD_FAST                2 (callback)
            108 POP_JUMP_IF_FALSE        9 (to 128)

195         110 NOP

196         112 PUSH_NULL
            114 LOAD_FAST                2 (callback)
            116 LOAD_FAST                1 (call_uuid)
            118 CALL                     1
            126 POP_TOP

201     >>  128 LOAD_FAST                0 (self)
            130 LOAD_ATTR               12 (active_calls)
            150 LOAD_ATTR                7 (NULL|self + pop)
            170 LOAD_FAST                1 (call_uuid)
            172 LOAD_CONST               2 (None)
            174 CALL                     2
            182 POP_TOP

202         184 LOAD_GLOBAL              0 (logger)
            194 LOAD_ATTR                3 (NULL|self + info)
            214 LOAD_CONST               5 ('[CallSessionManager] Cleaned up in-memory call context for ')
            216 LOAD_FAST                1 (call_uuid)
            218 FORMAT_VALUE             0
            220 BUILD_STRING             2
            222 CALL                     1
            230 POP_TOP
            232 RETURN_CONST             2 (None)
        >>  234 PUSH_EXC_INFO

197         236 LOAD_GLOBAL              8 (Exception)
            246 CHECK_EXC_MATCH
            248 POP_JUMP_IF_FALSE       37 (to 324)
            250 STORE_FAST               3 (e)

198         252 LOAD_GLOBAL              0 (logger)
            262 LOAD_ATTR               11 (NULL|self + error)
            282 LOAD_CONST               3 ('[CallSessionManager] Error during cleanup callback for ')
            284 LOAD_FAST                1 (call_uuid)
            286 FORMAT_VALUE             0
            288 LOAD_CONST               4 (': ')
            290 LOAD_FAST                3 (e)
            292 FORMAT_VALUE             0
            294 BUILD_STRING             4
            296 CALL                     1
            304 POP_TOP
            306 POP_EXCEPT
            308 LOAD_CONST               2 (None)
            310 STORE_FAST               3 (e)
            312 DELETE_FAST              3 (e)
            314 JUMP_BACKWARD           94 (to 128)
        >>  316 LOAD_CONST               2 (None)
            318 STORE_FAST               3 (e)
            320 DELETE_FAST              3 (e)
            322 RERAISE                  1

197     >>  324 RERAISE                  0
        >>  326 COPY                     3
            328 POP_EXCEPT
            330 RERAISE                  1
ExceptionTable:
  112 to 126 -> 234 [0]
  234 to 250 -> 326 [1] lasti
  252 to 304 -> 316 [1] lasti
  316 to 324 -> 326 [1] lasti

    Disassembling code object: __new__ at app\services\call_session_manager.py
    Constants: (None,)
    Names: ('_instance', 'super', 'CallSessionManager', '__new__', '_init')
    Varnames: ('cls', 'args', 'kwargs')
              0 COPY_FREE_VARS           1

 12           2 RESUME                   0

 13           4 LOAD_FAST                0 (cls)
              6 LOAD_ATTR                0 (_instance)
             26 POP_JUMP_IF_TRUE        54 (to 136)

 14          28 LOAD_GLOBAL              3 (NULL + super)
             38 LOAD_GLOBAL              4 (CallSessionManager)
             48 LOAD_FAST                0 (cls)
             50 LOAD_SUPER_ATTR         14 (__new__)
             54 LOAD_FAST                0 (cls)
             56 BUILD_LIST               1
             58 LOAD_FAST                1 (args)
             60 LIST_EXTEND              1
             62 CALL_INTRINSIC_1         6 (INTRINSIC_LIST_TO_TUPLE)
             64 BUILD_MAP                0
             66 LOAD_FAST                2 (kwargs)
             68 DICT_MERGE               1
             70 CALL_FUNCTION_EX         1
             72 LOAD_FAST                0 (cls)
             74 STORE_ATTR               0 (_instance)

 15          84 LOAD_FAST                0 (cls)
             86 LOAD_ATTR                0 (_instance)
            106 LOAD_ATTR                9 (NULL|self + _init)
            126 CALL                     0
            134 POP_TOP

 16     >>  136 LOAD_FAST                0 (cls)
            138 LOAD_ATTR                0 (_instance)
            158 RETURN_VALUE

    Disassembling code object: _init at app\services\call_session_manager.py
    Constants: (None,)
    Names: ('active_calls', 'cleanup_callbacks')
    Varnames: ('self',)
 18           0 RESUME                   0

 20           2 BUILD_MAP                0
              4 LOAD_FAST                0 (self)
              6 STORE_ATTR               0 (active_calls)

 22          16 BUILD_MAP                0
             18 LOAD_FAST                0 (self)
             20 STORE_ATTR               1 (cleanup_callbacks)
             30 RETURN_CONST             0 (None)

    Disassembling code object: register_inbound_asterisk_call at app\services\call_session_manager.py
    Constants: ('\n        Registers call metadata in active_calls dictionary.\n        ', '[CallSessionManager] Registering inbound call ', ' for agent ', 'asterisk', 'inbound', 'created', None, 0, ('call_uuid', 'caller_id', 'dialed_number', 'workspace_id', 'agent_id', 'phone_number_id', 'provider', 'direction', 'status', 'created_at', 'started_at', 'ended_at', 'agent_config', 'cost_cents'))
    Names: ('logger', 'info', 'datetime', 'now', 'timezone', 'utc', 'isoformat', 'active_calls')
    Varnames: ('self', 'call_uuid', 'caller_id', 'dialed_number', 'workspace_id', 'agent_id', 'phone_number_id', 'context')
 24           0 RESUME                   0

 36           2 LOAD_GLOBAL              0 (logger)
             12 LOAD_ATTR                3 (NULL|self + info)
             32 LOAD_CONST               1 ('[CallSessionManager] Registering inbound call ')
             34 LOAD_FAST                1 (call_uuid)
             36 FORMAT_VALUE             0
             38 LOAD_CONST               2 (' for agent ')
             40 LOAD_FAST                5 (agent_id)
             42 FORMAT_VALUE             0
             44 BUILD_STRING             4
             46 CALL                     1
             54 POP_TOP

 38          56 LOAD_FAST                1 (call_uuid)

 39          58 LOAD_FAST                2 (caller_id)

 40          60 LOAD_FAST                3 (dialed_number)

 41          62 LOAD_FAST                4 (workspace_id)

 42          64 LOAD_FAST                5 (agent_id)

 43          66 LOAD_FAST                6 (phone_number_id)

 44          68 LOAD_CONST               3 ('asterisk')

 45          70 LOAD_CONST               4 ('inbound')

 46          72 LOAD_CONST               5 ('created')

 47          74 LOAD_GLOBAL              5 (NULL + datetime)
             84 LOAD_ATTR                6 (now)
            104 LOAD_GLOBAL              8 (timezone)
            114 LOAD_ATTR               10 (utc)
            134 CALL                     1
            142 LOAD_ATTR               13 (NULL|self + isoformat)
            162 CALL                     0

 48         170 LOAD_CONST               6 (None)

 49         172 LOAD_CONST               6 (None)

 50         174 BUILD_MAP                0

 51         176 LOAD_CONST               7 (0)

 37         178 LOAD_CONST               8 (('call_uuid', 'caller_id', 'dialed_number', 'workspace_id', 'agent_id', 'phone_number_id', 'provider', 'direction', 'status', 'created_at', 'started_at', 'ended_at', 'agent_config', 'cost_cents'))
            180 BUILD_CONST_KEY_MAP     14
            182 STORE_FAST               7 (context)

 53         184 LOAD_FAST                7 (context)
            186 LOAD_FAST                0 (self)
            188 LOAD_ATTR               14 (active_calls)
            208 LOAD_FAST                1 (call_uuid)
            210 STORE_SUBSCR

 54         214 LOAD_FAST                7 (context)
            216 RETURN_VALUE

    Disassembling code object: get_call_context at app\services\call_session_manager.py
    Constants: ('\n        Gets call context. If agent_config is not loaded, loads it from Supabase.\n        ', <code object _query at 0x000001CAC3E78DF0, file "app\services\call_session_manager.py", line 64>, None, 0, 'caller_id', 'caller_phone_number', '', 'dialed_number', 'workspace_id', 'agent_id', 'phone_number_id', ('call_uuid', 'caller_id', 'dialed_number', 'workspace_id', 'agent_id', 'phone_number_id'), 'status', '[CallSessionManager] DB recovery lookup failed for ', ': ', 'agent_config', <code object _get_agent at 0x000001CAC3E78A30, file "app\services\call_session_manager.py", line 92>, 'kb_metadata', 'name', 'model', 'language', 'hi-IN', 'voice_id', 'aura-asteria-en', 'tts_provider', 'deepgram', 'system_prompt', 'knowledge_base', 'voice_gender', 'female', ('name', 'model', 'language', 'voice_id', 'tts_provider', 'system_prompt', 'knowledge_base', 'voice_gender'), '[CallSessionManager] Loaded agent config for call ', '[CallSessionManager] Failed to load agent details for call ')
    Names: ('active_calls', 'get', 'get_supabase_client', 'asyncio', 'to_thread', 'data', 'register_inbound_asterisk_call', 'Exception', 'logger', 'error', 'info')
    Varnames: ('self', 'call_uuid', 'context', '_query', 'res', 'row', 'e', '_get_agent', 'agent_res', 'agent', 'kb_meta')
              0 MAKE_CELL                1 (call_uuid)
              2 MAKE_CELL               11 (agent_id)
              4 MAKE_CELL               12 (db)

 56           6 RETURN_GENERATOR
              8 POP_TOP
             10 RESUME                   0

 60          12 LOAD_FAST                0 (self)
             14 LOAD_ATTR                0 (active_calls)
             34 LOAD_ATTR                3 (NULL|self + get)
             54 LOAD_DEREF               1 (call_uuid)
             56 CALL                     1
             64 STORE_FAST               2 (context)

 61          66 LOAD_FAST                2 (context)
             68 POP_JUMP_IF_TRUE       218 (to 506)

 63          70 LOAD_GLOBAL              5 (NULL + get_supabase_client)
             80 CALL                     0
             88 STORE_DEREF             12 (db)

 64          90 LOAD_CLOSURE             1 (call_uuid)
             92 LOAD_CLOSURE            12 (db)
             94 BUILD_TUPLE              2
             96 LOAD_CONST               1 (<code object _query at 0x000001CAC3E78DF0, file "app\services\call_session_manager.py", line 64>)
             98 MAKE_FUNCTION            8 (closure)
            100 STORE_FAST               3 (_query)

 67         102 NOP

 68         104 LOAD_GLOBAL              7 (NULL + asyncio)
            114 LOAD_ATTR                8 (to_thread)
            134 LOAD_FAST                3 (_query)
            136 CALL                     1
            144 GET_AWAITABLE            0
            146 LOAD_CONST               2 (None)
        >>  148 SEND                     3 (to 158)
            152 YIELD_VALUE              3
            154 RESUME                   3
            156 JUMP_BACKWARD_NO_INTERRUPT     5 (to 148)
        >>  158 END_SEND
            160 STORE_FAST               4 (res)

 69         162 LOAD_FAST                4 (res)
            164 LOAD_ATTR               10 (data)
            184 POP_JUMP_IF_FALSE      160 (to 506)

 70         186 LOAD_FAST                4 (res)
            188 LOAD_ATTR               10 (data)
            208 LOAD_CONST               3 (0)
            210 BINARY_SUBSCR
            214 STORE_FAST               5 (row)

 71         216 LOAD_FAST                0 (self)
            218 LOAD_ATTR               13 (NULL|self + register_inbound_asterisk_call)

 72         238 LOAD_DEREF               1 (call_uuid)

 73         240 LOAD_FAST                5 (row)
            242 LOAD_ATTR                3 (NULL|self + get)
            262 LOAD_CONST               4 ('caller_id')
            264 CALL                     1
            272 COPY                     1
            274 POP_JUMP_IF_TRUE        21 (to 318)
            276 POP_TOP
            278 LOAD_FAST                5 (row)
            280 LOAD_ATTR                3 (NULL|self + get)
            300 LOAD_CONST               5 ('caller_phone_number')
            302 CALL                     1
            310 COPY                     1
            312 POP_JUMP_IF_TRUE         2 (to 318)
            314 POP_TOP
            316 LOAD_CONST               6 ('')

 74     >>  318 LOAD_FAST                5 (row)
            320 LOAD_ATTR                3 (NULL|self + get)
            340 LOAD_CONST               7 ('dialed_number')
            342 CALL                     1
            350 COPY                     1
            352 POP_JUMP_IF_TRUE         2 (to 358)
            354 POP_TOP
            356 LOAD_CONST               6 ('')

 75     >>  358 LOAD_FAST                5 (row)
            360 LOAD_ATTR                3 (NULL|self + get)
            380 LOAD_CONST               8 ('workspace_id')
            382 CALL                     1

 76         390 LOAD_FAST                5 (row)
            392 LOAD_ATTR                3 (NULL|self + get)
            412 LOAD_CONST               9 ('agent_id')
            414 CALL                     1

 77         422 LOAD_FAST                5 (row)
            424 LOAD_ATTR                3 (NULL|self + get)
            444 LOAD_CONST              10 ('phone_number_id')
            446 CALL                     1

 71         454 KW_NAMES                11 (('call_uuid', 'caller_id', 'dialed_number', 'workspace_id', 'agent_id', 'phone_number_id'))
            456 CALL                     6
            464 STORE_FAST               2 (context)

 79         466 LOAD_FAST                5 (row)
            468 LOAD_ATTR                3 (NULL|self + get)
            488 LOAD_CONST              12 ('status')
            490 CALL                     1
            498 LOAD_FAST                2 (context)
            500 LOAD_CONST              12 ('status')
            502 STORE_SUBSCR

 84     >>  506 LOAD_FAST                2 (context)
            508 POP_JUMP_IF_TRUE         1 (to 512)

 85         510 RETURN_CONST             2 (None)

 88     >>  512 LOAD_FAST                2 (context)
            514 LOAD_ATTR                3 (NULL|self + get)
            534 LOAD_CONST              15 ('agent_config')
            536 CALL                     1
            544 EXTENDED_ARG             1
            546 POP_JUMP_IF_TRUE       283 (to 1114)

 89         548 LOAD_GLOBAL              5 (NULL + get_supabase_client)
            558 CALL                     0
            566 STORE_DEREF             12 (db)

 90         568 LOAD_FAST                2 (context)
            570 LOAD_CONST               9 ('agent_id')
            572 BINARY_SUBSCR
            576 STORE_DEREF             11 (agent_id)

 92         578 LOAD_CLOSURE            11 (agent_id)
            580 LOAD_CLOSURE            12 (db)
            582 BUILD_TUPLE              2
            584 LOAD_CONST              16 (<code object _get_agent at 0x000001CAC3E78A30, file "app\services\call_session_manager.py", line 92>)
            586 MAKE_FUNCTION            8 (closure)
            588 STORE_FAST               7 (_get_agent)

 95         590 NOP

 96         592 LOAD_GLOBAL              7 (NULL + asyncio)
            602 LOAD_ATTR                8 (to_thread)
            622 LOAD_FAST                7 (_get_agent)
            624 CALL                     1
            632 GET_AWAITABLE            0
            634 LOAD_CONST               2 (None)
        >>  636 SEND                     3 (to 646)
            640 YIELD_VALUE              3
            642 RESUME                   3
            644 JUMP_BACKWARD_NO_INTERRUPT     5 (to 636)
        >>  646 END_SEND
            648 STORE_FAST               8 (agent_res)

 97         650 LOAD_FAST                8 (agent_res)
            652 LOAD_ATTR               10 (data)
            672 POP_JUMP_IF_FALSE      218 (to 1110)

 98         674 LOAD_FAST                8 (agent_res)
            676 LOAD_ATTR               10 (data)
            696 LOAD_CONST               3 (0)
            698 BINARY_SUBSCR
            702 STORE_FAST               9 (agent)

 99         704 LOAD_FAST                9 (agent)
            706 LOAD_ATTR                3 (NULL|self + get)
            726 LOAD_CONST              17 ('kb_metadata')
            728 CALL                     1
            736 COPY                     1
            738 POP_JUMP_IF_TRUE         2 (to 744)
            740 POP_TOP
            742 BUILD_MAP                0
        >>  744 STORE_FAST              10 (kb_meta)

101         746 LOAD_FAST                9 (agent)
            748 LOAD_ATTR                3 (NULL|self + get)
            768 LOAD_CONST              18 ('name')
            770 CALL                     1

102         778 LOAD_FAST                9 (agent)
            780 LOAD_ATTR                3 (NULL|self + get)
            800 LOAD_CONST              19 ('model')
            802 CALL                     1

103         810 LOAD_FAST                9 (agent)
            812 LOAD_ATTR                3 (NULL|self + get)
            832 LOAD_CONST              20 ('language')
            834 CALL                     1
            842 COPY                     1
            844 POP_JUMP_IF_TRUE         2 (to 850)
            846 POP_TOP
            848 LOAD_CONST              21 ('hi-IN')

104     >>  850 LOAD_FAST                9 (agent)
            852 LOAD_ATTR                3 (NULL|self + get)
            872 LOAD_CONST              22 ('voice_id')
            874 CALL                     1
            882 COPY                     1
            884 POP_JUMP_IF_TRUE         2 (to 890)
            886 POP_TOP
            888 LOAD_CONST              23 ('aura-asteria-en')

105     >>  890 LOAD_FAST               10 (kb_meta)
            892 LOAD_ATTR                3 (NULL|self + get)
            912 LOAD_CONST              24 ('tts_provider')
            914 CALL                     1
            922 COPY                     1
            924 POP_JUMP_IF_TRUE         2 (to 930)
            926 POP_TOP
            928 LOAD_CONST              25 ('deepgram')

106     >>  930 LOAD_FAST                9 (agent)
            932 LOAD_ATTR                3 (NULL|self + get)
            952 LOAD_CONST              26 ('system_prompt')
            954 CALL                     1
            962 COPY                     1
            964 POP_JUMP_IF_TRUE         2 (to 970)
            966 POP_TOP
            968 LOAD_CONST               6 ('')

107     >>  970 LOAD_FAST                9 (agent)
            972 LOAD_ATTR                3 (NULL|self + get)
            992 LOAD_CONST              27 ('knowledge_base')
            994 CALL                     1
           1002 COPY                     1
           1004 POP_JUMP_IF_TRUE         2 (to 1010)
           1006 POP_TOP
           1008 LOAD_CONST               6 ('')

108     >> 1010 LOAD_FAST               10 (kb_meta)
           1012 LOAD_ATTR                3 (NULL|self + get)
           1032 LOAD_CONST              28 ('voice_gender')
           1034 CALL                     1
           1042 COPY                     1
           1044 POP_JUMP_IF_TRUE         2 (to 1050)
           1046 POP_TOP
           1048 LOAD_CONST              29 ('female')

100     >> 1050 LOAD_CONST              30 (('name', 'model', 'language', 'voice_id', 'tts_provider', 'system_prompt', 'knowledge_base', 'voice_gender'))
           1052 BUILD_CONST_KEY_MAP      8
           1054 LOAD_FAST                2 (context)
           1056 LOAD_CONST              15 ('agent_config')
           1058 STORE_SUBSCR

110        1062 LOAD_GLOBAL             16 (logger)
           1072 LOAD_ATTR               21 (NULL|self + info)
           1092 LOAD_CONST              31 ('[CallSessionManager] Loaded agent config for call ')
           1094 LOAD_DEREF               1 (call_uuid)
           1096 FORMAT_VALUE             0
           1098 BUILD_STRING             2
           1100 CALL                     1
           1108 POP_TOP

114     >> 1110 LOAD_FAST                2 (context)
           1112 RETURN_VALUE
        >> 1114 LOAD_FAST                2 (context)
           1116 RETURN_VALUE

 68     >> 1118 CLEANUP_THROW
           1120 EXTENDED_ARG             1
           1122 JUMP_BACKWARD          483 (to 158)
        >> 1124 PUSH_EXC_INFO

 80        1126 LOAD_GLOBAL             14 (Exception)
           1136 CHECK_EXC_MATCH
           1138 POP_JUMP_IF_FALSE       37 (to 1214)
           1140 STORE_FAST               6 (e)

 81        1142 LOAD_GLOBAL             16 (logger)
           1152 LOAD_ATTR               19 (NULL|self + error)
           1172 LOAD_CONST              13 ('[CallSessionManager] DB recovery lookup failed for ')
           1174 LOAD_DEREF               1 (call_uuid)
           1176 FORMAT_VALUE             0
           1178 LOAD_CONST              14 (': ')
           1180 LOAD_FAST                6 (e)
           1182 FORMAT_VALUE             0
           1184 BUILD_STRING             4
           1186 CALL                     1
           1194 POP_TOP

 82        1196 POP_EXCEPT
           1198 LOAD_CONST               2 (None)
           1200 STORE_FAST               6 (e)
           1202 DELETE_FAST              6 (e)
           1204 RETURN_CONST             2 (None)
        >> 1206 LOAD_CONST               2 (None)
           1208 STORE_FAST               6 (e)
           1210 DELETE_FAST              6 (e)
           1212 RERAISE                  1

 80     >> 1214 RERAISE                  0
        >> 1216 COPY                     3
           1218 POP_EXCEPT
           1220 RERAISE                  1

 96     >> 1222 CLEANUP_THROW
           1224 EXTENDED_ARG             1
           1226 JUMP_BACKWARD          291 (to 646)
        >> 1228 PUSH_EXC_INFO

111        1230 LOAD_GLOBAL             14 (Exception)
           1240 CHECK_EXC_MATCH
           1242 POP_JUMP_IF_FALSE       38 (to 1320)
           1244 STORE_FAST               6 (e)

112        1246 LOAD_GLOBAL             16 (logger)
           1256 LOAD_ATTR               19 (NULL|self + error)
           1276 LOAD_CONST              32 ('[CallSessionManager] Failed to load agent details for call ')
           1278 LOAD_DEREF               1 (call_uuid)
           1280 FORMAT_VALUE             0
           1282 LOAD_CONST              14 (': ')
           1284 LOAD_FAST                6 (e)
           1286 FORMAT_VALUE             0
           1288 BUILD_STRING             4
           1290 CALL                     1
           1298 POP_TOP
           1300 POP_EXCEPT
           1302 LOAD_CONST               2 (None)
           1304 STORE_FAST               6 (e)
           1306 DELETE_FAST              6 (e)

114        1308 LOAD_FAST                2 (context)
           1310 RETURN_VALUE
        >> 1312 LOAD_CONST               2 (None)
           1314 STORE_FAST               6 (e)
           1316 DELETE_FAST              6 (e)
           1318 RERAISE                  1

111     >> 1320 RERAISE                  0
        >> 1322 COPY                     3
           1324 POP_EXCEPT
           1326 RERAISE                  1
        >> 1328 CALL_INTRINSIC_1         3 (INTRINSIC_STOPITERATION_ERROR)
           1330 RERAISE                  1
ExceptionTable:
  10 to 100 -> 1328 [0] lasti
  104 to 150 -> 1124 [0]
  152 to 152 -> 1118 [2]
  154 to 504 -> 1124 [0]
  506 to 588 -> 1328 [0] lasti
  592 to 638 -> 1228 [0]
  640 to 640 -> 1222 [2]
  642 to 1108 -> 1228 [0]
  1110 to 1116 -> 1328 [0] lasti
  1118 to 1118 -> 1124 [0]
  1124 to 1140 -> 1216 [1] lasti
  1142 to 1194 -> 1206 [1] lasti
  1196 to 1204 -> 1328 [0] lasti
  1206 to 1214 -> 1216 [1] lasti
  1216 to 1220 -> 1328 [0] lasti
  1222 to 1222 -> 1228 [0]
  1228 to 1244 -> 1322 [1] lasti
  1246 to 1298 -> 1312 [1] lasti
  1300 to 1310 -> 1328 [0] lasti
  1312 to 1320 -> 1322 [1] lasti
  1322 to 1326 -> 1328 [0] lasti

Disassembly of <code object _query at 0x000001CAC3E78DF0, file "app\services\call_session_manager.py", line 64>:
              0 COPY_FREE_VARS           2

 64           2 RESUME                   0

 65           4 LOAD_DEREF               1 (db)
              6 LOAD_ATTR                1 (NULL|self + table)
             26 LOAD_CONST               1 ('calls')
             28 CALL                     1
             36 LOAD_ATTR                3 (NULL|self + select)
             56 LOAD_CONST               2 ('*')
             58 CALL                     1
             66 LOAD_ATTR                5 (NULL|self + eq)
             86 LOAD_CONST               3 ('call_uuid')
             88 LOAD_DEREF               0 (call_uuid)
             90 CALL                     2
             98 LOAD_ATTR                7 (NULL|self + execute)
            118 CALL                     0
            126 RETURN_VALUE

Disassembly of <code object _get_agent at 0x000001CAC3E78A30, file "app\services\call_session_manager.py", line 92>:
              0 COPY_FREE_VARS           2

 92           2 RESUME                   0

 93           4 LOAD_DEREF               1 (db)
              6 LOAD_ATTR                1 (NULL|self + table)
             26 LOAD_CONST               1 ('agents')
             28 CALL                     1
             36 LOAD_ATTR                3 (NULL|self + select)
             56 LOAD_CONST               2 ('*')
             58 CALL                     1
             66 LOAD_ATTR                5 (NULL|self + eq)
             86 LOAD_CONST               3 ('id')
             88 LOAD_DEREF               0 (agent_id)
             90 CALL                     2
             98 LOAD_ATTR                7 (NULL|self + execute)
            118 CALL                     0
            126 RETURN_VALUE

      Disassembling code object: _query at app\services\call_session_manager.py
      Constants: (None, 'calls', '*', 'call_uuid')
      Names: ('table', 'select', 'eq', 'execute')
      Varnames: ()
              0 COPY_FREE_VARS           2

 64           2 RESUME                   0

 65           4 LOAD_DEREF               1 (db)
              6 LOAD_ATTR                1 (NULL|self + table)
             26 LOAD_CONST               1 ('calls')
             28 CALL                     1
             36 LOAD_ATTR                3 (NULL|self + select)
             56 LOAD_CONST               2 ('*')
             58 CALL                     1
             66 LOAD_ATTR                5 (NULL|self + eq)
             86 LOAD_CONST               3 ('call_uuid')
             88 LOAD_DEREF               0 (call_uuid)
             90 CALL                     2
             98 LOAD_ATTR                7 (NULL|self + execute)
            118 CALL                     0
            126 RETURN_VALUE

      Disassembling code object: _get_agent at app\services\call_session_manager.py
      Constants: (None, 'agents', '*', 'id')
      Names: ('table', 'select', 'eq', 'execute')
      Varnames: ()
              0 COPY_FREE_VARS           2

 92           2 RESUME                   0

 93           4 LOAD_DEREF               1 (db)
              6 LOAD_ATTR                1 (NULL|self + table)
             26 LOAD_CONST               1 ('agents')
             28 CALL                     1
             36 LOAD_ATTR                3 (NULL|self + select)
             56 LOAD_CONST               2 ('*')
             58 CALL                     1
             66 LOAD_ATTR                5 (NULL|self + eq)
             86 LOAD_CONST               3 ('id')
             88 LOAD_DEREF               0 (agent_id)
             90 CALL                     2
             98 LOAD_ATTR                7 (NULL|self + execute)
            118 CALL                     0
            126 RETURN_VALUE

    Disassembling code object: start_audio_session at app\services\call_session_manager.py
    Constants: ('\n        Marks call status as in_progress and updates started_at.\n        ', False, 'in_progress', 'status', 'started_at', '[CallSessionManager] Audio session started for ', <code object _update at 0x000001CAC3E50E30, file "app\services\call_session_manager.py", line 129>, True)
    Names: ('active_calls', 'get', 'datetime', 'now', 'timezone', 'utc', 'isoformat', 'logger', 'info', 'get_supabase_client', 'asyncio', 'create_task', 'to_thread')
    Varnames: ('self', 'call_uuid', '_update')
              0 MAKE_CELL                1 (call_uuid)
              2 MAKE_CELL                3 (context)
              4 MAKE_CELL                4 (db)

116           6 RESUME                   0

120           8 LOAD_FAST                0 (self)
             10 LOAD_ATTR                0 (active_calls)
             30 LOAD_ATTR                3 (NULL|self + get)
             50 LOAD_DEREF               1 (call_uuid)
             52 CALL                     1
             60 STORE_DEREF              3 (context)

121          62 LOAD_DEREF               3 (context)
             64 POP_JUMP_IF_TRUE         1 (to 68)

122          66 RETURN_CONST             1 (False)

123     >>   68 LOAD_CONST               2 ('in_progress')
             70 LOAD_DEREF               3 (context)
             72 LOAD_CONST               3 ('status')
             74 STORE_SUBSCR

124          78 LOAD_GLOBAL              5 (NULL + datetime)
             88 LOAD_ATTR                6 (now)
            108 LOAD_GLOBAL              8 (timezone)
            118 LOAD_ATTR               10 (utc)
            138 CALL                     1
            146 LOAD_ATTR               13 (NULL|self + isoformat)
            166 CALL                     0
            174 LOAD_DEREF               3 (context)
            176 LOAD_CONST               4 ('started_at')
            178 STORE_SUBSCR

125         182 LOAD_GLOBAL             14 (logger)
            192 LOAD_ATTR               17 (NULL|self + info)
            212 LOAD_CONST               5 ('[CallSessionManager] Audio session started for ')
            214 LOAD_DEREF               1 (call_uuid)
            216 FORMAT_VALUE             0
            218 BUILD_STRING             2
            220 CALL                     1
            228 POP_TOP

128         230 LOAD_GLOBAL             19 (NULL + get_supabase_client)
            240 CALL                     0
            248 STORE_DEREF              4 (db)

129         250 LOAD_CLOSURE             1 (call_uuid)
            252 LOAD_CLOSURE             3 (context)
            254 LOAD_CLOSURE             4 (db)
            256 BUILD_TUPLE              3
            258 LOAD_CONST               6 (<code object _update at 0x000001CAC3E50E30, file "app\services\call_session_manager.py", line 129>)
            260 MAKE_FUNCTION            8 (closure)
            262 STORE_FAST               2 (_update)

138         264 LOAD_GLOBAL             21 (NULL + asyncio)
            274 LOAD_ATTR               22 (create_task)
            294 LOAD_GLOBAL             21 (NULL + asyncio)
            304 LOAD_ATTR               24 (to_thread)
            324 LOAD_FAST                2 (_update)
            326 CALL                     1
            334 CALL                     1
            342 POP_TOP

139         344 RETURN_CONST             7 (True)

Disassembly of <code object _update at 0x000001CAC3E50E30, file "app\services\call_session_manager.py", line 129>:
              0 COPY_FREE_VARS           3

129           2 RESUME                   0

130           4 NOP

131           6 LOAD_DEREF               3 (db)
              8 LOAD_ATTR                1 (NULL|self + table)
             28 LOAD_CONST               1 ('calls')
             30 CALL                     1
             38 LOAD_ATTR                3 (NULL|self + update)

132          58 LOAD_CONST               2 ('in_progress')

133          60 LOAD_DEREF               2 (context)
             62 LOAD_CONST               3 ('started_at')
             64 BINARY_SUBSCR

131          68 LOAD_CONST               4 (('status', 'started_at'))
             70 BUILD_CONST_KEY_MAP      2
             72 CALL                     1

134          80 LOAD_ATTR                5 (NULL|self + eq)
            100 LOAD_CONST               5 ('call_uuid')
            102 LOAD_DEREF               1 (call_uuid)
            104 CALL                     2
            112 LOAD_ATTR                7 (NULL|self + execute)
            132 CALL                     0
            140 POP_TOP
            142 RETURN_CONST             0 (None)
        >>  144 PUSH_EXC_INFO

135         146 LOAD_GLOBAL              8 (Exception)
            156 CHECK_EXC_MATCH
            158 POP_JUMP_IF_FALSE       37 (to 234)
            160 STORE_FAST               0 (e)

136         162 LOAD_GLOBAL             10 (logger)
            172 LOAD_ATTR               13 (NULL|self + error)
            192 LOAD_CONST               6 ('[CallSessionManager] DB status update error for ')
            194 LOAD_DEREF               1 (call_uuid)
            196 FORMAT_VALUE             0
            198 LOAD_CONST               7 (': ')
            200 LOAD_FAST                0 (e)
            202 FORMAT_VALUE             0
            204 BUILD_STRING             4
            206 CALL                     1
            214 POP_TOP
            216 POP_EXCEPT
            218 LOAD_CONST               0 (None)
            220 STORE_FAST               0 (e)
            222 DELETE_FAST              0 (e)
            224 RETURN_CONST             0 (None)
        >>  226 LOAD_CONST               0 (None)
            228 STORE_FAST               0 (e)
            230 DELETE_FAST              0 (e)
            232 RERAISE                  1

135     >>  234 RERAISE                  0
        >>  236 COPY                     3
            238 POP_EXCEPT
            240 RERAISE                  1
ExceptionTable:
  6 to 140 -> 144 [0]
  144 to 160 -> 236 [1] lasti
  162 to 214 -> 226 [1] lasti
  226 to 234 -> 236 [1] lasti

      Disassembling code object: _update at app\services\call_session_manager.py
      Constants: (None, 'calls', 'in_progress', 'started_at', ('status', 'started_at'), 'call_uuid', '[CallSessionManager] DB status update error for ', ': ')
      Names: ('table', 'update', 'eq', 'execute', 'Exception', 'logger', 'error')
      Varnames: ('e',)
              0 COPY_FREE_VARS           3

129           2 RESUME                   0

130           4 NOP

131           6 LOAD_DEREF               3 (db)
              8 LOAD_ATTR                1 (NULL|self + table)
             28 LOAD_CONST               1 ('calls')
             30 CALL                     1
             38 LOAD_ATTR                3 (NULL|self + update)

132          58 LOAD_CONST               2 ('in_progress')

133          60 LOAD_DEREF               2 (context)
             62 LOAD_CONST               3 ('started_at')
             64 BINARY_SUBSCR

131          68 LOAD_CONST               4 (('status', 'started_at'))
             70 BUILD_CONST_KEY_MAP      2
             72 CALL                     1

134          80 LOAD_ATTR                5 (NULL|self + eq)
            100 LOAD_CONST               5 ('call_uuid')
            102 LOAD_DEREF               1 (call_uuid)
            104 CALL                     2
            112 LOAD_ATTR                7 (NULL|self + execute)
            132 CALL                     0
            140 POP_TOP
            142 RETURN_CONST             0 (None)
        >>  144 PUSH_EXC_INFO

135         146 LOAD_GLOBAL              8 (Exception)
            156 CHECK_EXC_MATCH
            158 POP_JUMP_IF_FALSE       37 (to 234)
            160 STORE_FAST               0 (e)

136         162 LOAD_GLOBAL             10 (logger)
            172 LOAD_ATTR               13 (NULL|self + error)
            192 LOAD_CONST               6 ('[CallSessionManager] DB status update error for ')
            194 LOAD_DEREF               1 (call_uuid)
            196 FORMAT_VALUE             0
            198 LOAD_CONST               7 (': ')
            200 LOAD_FAST                0 (e)
            202 FORMAT_VALUE             0
            204 BUILD_STRING             4
            206 CALL                     1
            214 POP_TOP
            216 POP_EXCEPT
            218 LOAD_CONST               0 (None)
            220 STORE_FAST               0 (e)
            222 DELETE_FAST              0 (e)
            224 RETURN_CONST             0 (None)
        >>  226 LOAD_CONST               0 (None)
            228 STORE_FAST               0 (e)
            230 DELETE_FAST              0 (e)
            232 RERAISE                  1

135     >>  234 RERAISE                  0
        >>  236 COPY                     3
            238 POP_EXCEPT
            240 RERAISE                  1
ExceptionTable:
  6 to 140 -> 144 [0]
  144 to 160 -> 236 [1] lasti
  162 to 214 -> 226 [1] lasti
  226 to 234 -> 236 [1] lasti

    Disassembling code object: end_call at app\services\call_session_manager.py
    Constants: ('\n        Ends call, updates status, ended_at and triggers DB updates.\n        ', False, 'completed', 'status', 'ended_at', 'end_reason', 0, 'started_at', 'Z', '+00:00', '[CallSessionManager] Error calculating duration for ', ': ', None, 'duration_seconds', '[CallSessionManager] Call ', ' ended. Reason: ', ', Duration: ', 's', <code object _update at 0x000001CAC3E52870, file "app\services\call_session_manager.py", line 168>, True)
    Names: ('active_calls', 'get', 'datetime', 'now', 'timezone', 'utc', 'isoformat', 'fromisoformat', 'replace', 'int', 'total_seconds', 'Exception', 'logger', 'error', 'info', 'get_supabase_client', 'asyncio', 'create_task', 'to_thread')
    Varnames: ('self', 'call_uuid', 'reason', 'start_dt', 'end_dt', 'e', '_update')
              0 MAKE_CELL                1 (call_uuid)
              2 MAKE_CELL                2 (reason)
              4 MAKE_CELL                7 (context)
              6 MAKE_CELL                8 (db)
              8 MAKE_CELL                9 (duration)

141          10 RESUME                   0

145          12 LOAD_FAST                0 (self)
             14 LOAD_ATTR                0 (active_calls)
             34 LOAD_ATTR                3 (NULL|self + get)
             54 LOAD_DEREF               1 (call_uuid)
             56 CALL                     1
             64 STORE_DEREF              7 (context)

146          66 LOAD_DEREF               7 (context)
             68 POP_JUMP_IF_TRUE         1 (to 72)

147          70 RETURN_CONST             1 (False)

149     >>   72 LOAD_CONST               2 ('completed')
             74 LOAD_DEREF               7 (context)
             76 LOAD_CONST               3 ('status')
             78 STORE_SUBSCR

150          82 LOAD_GLOBAL              5 (NULL + datetime)
             92 LOAD_ATTR                6 (now)
            112 LOAD_GLOBAL              8 (timezone)
            122 LOAD_ATTR               10 (utc)
            142 CALL                     1
            150 LOAD_ATTR               13 (NULL|self + isoformat)
            170 CALL                     0
            178 LOAD_DEREF               7 (context)
            180 LOAD_CONST               4 ('ended_at')
            182 STORE_SUBSCR

151         186 LOAD_DEREF               2 (reason)
            188 LOAD_DEREF               7 (context)
            190 LOAD_CONST               5 ('end_reason')
            192 STORE_SUBSCR

154         196 LOAD_CONST               6 (0)
            198 STORE_DEREF              9 (duration)

155         200 LOAD_DEREF               7 (context)
            202 LOAD_ATTR                3 (NULL|self + get)
            222 LOAD_CONST               7 ('started_at')
            224 CALL                     1
            232 POP_JUMP_IF_FALSE      109 (to 452)

156         234 NOP

157         236 LOAD_GLOBAL              5 (NULL + datetime)
            246 LOAD_ATTR               14 (fromisoformat)
            266 LOAD_DEREF               7 (context)
            268 LOAD_CONST               7 ('started_at')
            270 BINARY_SUBSCR
            274 LOAD_ATTR               17 (NULL|self + replace)
            294 LOAD_CONST               8 ('Z')
            296 LOAD_CONST               9 ('+00:00')
            298 CALL                     2
            306 CALL                     1
            314 STORE_FAST               3 (start_dt)

158         316 LOAD_GLOBAL              5 (NULL + datetime)
            326 LOAD_ATTR               14 (fromisoformat)
            346 LOAD_DEREF               7 (context)
            348 LOAD_CONST               4 ('ended_at')
            350 BINARY_SUBSCR
            354 LOAD_ATTR               17 (NULL|self + replace)
            374 LOAD_CONST               8 ('Z')
            376 LOAD_CONST               9 ('+00:00')
            378 CALL                     2
            386 CALL                     1
            394 STORE_FAST               4 (end_dt)

159         396 LOAD_GLOBAL             19 (NULL + int)
            406 LOAD_FAST                4 (end_dt)
            408 LOAD_FAST                3 (start_dt)
            410 BINARY_OP               10 (-)
            414 LOAD_ATTR               21 (NULL|self + total_seconds)
            434 CALL                     0
            442 CALL                     1
            450 STORE_DEREF              9 (duration)

162     >>  452 LOAD_DEREF               9 (duration)
            454 LOAD_DEREF               7 (context)
            456 LOAD_CONST              13 ('duration_seconds')
            458 STORE_SUBSCR

164         462 LOAD_GLOBAL             24 (logger)
            472 LOAD_ATTR               29 (NULL|self + info)
            492 LOAD_CONST              14 ('[CallSessionManager] Call ')
            494 LOAD_DEREF               1 (call_uuid)
            496 FORMAT_VALUE             0
            498 LOAD_CONST              15 (' ended. Reason: ')
            500 LOAD_DEREF               2 (reason)
            502 FORMAT_VALUE             0
            504 LOAD_CONST              16 (', Duration: ')
            506 LOAD_DEREF               9 (duration)
            508 FORMAT_VALUE             0
            510 LOAD_CONST              17 ('s')
            512 BUILD_STRING             7
            514 CALL                     1
            522 POP_TOP

167         524 LOAD_GLOBAL             31 (NULL + get_supabase_client)
            534 CALL                     0
            542 STORE_DEREF              8 (db)

168         544 LOAD_CLOSURE             1 (call_uuid)
            546 LOAD_CLOSURE             7 (context)
            548 LOAD_CLOSURE             8 (db)
            550 LOAD_CLOSURE             9 (duration)
            552 LOAD_CLOSURE             2 (reason)
            554 BUILD_TUPLE              5
            556 LOAD_CONST              18 (<code object _update at 0x000001CAC3E52870, file "app\services\call_session_manager.py", line 168>)
            558 MAKE_FUNCTION            8 (closure)
            560 STORE_FAST               6 (_update)

180         562 LOAD_GLOBAL             33 (NULL + asyncio)
            572 LOAD_ATTR               34 (create_task)
            592 LOAD_GLOBAL             33 (NULL + asyncio)
            602 LOAD_ATTR               36 (to_thread)
            622 LOAD_FAST                6 (_update)
            624 CALL                     1
            632 CALL                     1
            640 POP_TOP

181         642 RETURN_CONST            19 (True)
        >>  644 PUSH_EXC_INFO

160         646 LOAD_GLOBAL             22 (Exception)
            656 CHECK_EXC_MATCH
            658 POP_JUMP_IF_FALSE       37 (to 734)
            660 STORE_FAST               5 (e)

161         662 LOAD_GLOBAL             24 (logger)
            672 LOAD_ATTR               27 (NULL|self + error)
            692 LOAD_CONST              10 ('[CallSessionManager] Error calculating duration for ')
            694 LOAD_DEREF               1 (call_uuid)
            696 FORMAT_VALUE             0
            698 LOAD_CONST              11 (': ')
            700 LOAD_FAST                5 (e)
            702 FORMAT_VALUE             0
            704 BUILD_STRING             4
            706 CALL                     1
            714 POP_TOP
            716 POP_EXCEPT
            718 LOAD_CONST              12 (None)
            720 STORE_FAST               5 (e)
            722 DELETE_FAST              5 (e)
            724 JUMP_BACKWARD          137 (to 452)
        >>  726 LOAD_CONST              12 (None)
            728 STORE_FAST               5 (e)
            730 DELETE_FAST              5 (e)
            732 RERAISE                  1

160     >>  734 RERAISE                  0
        >>  736 COPY                     3
            738 POP_EXCEPT
            740 RERAISE                  1
ExceptionTable:
  236 to 450 -> 644 [0]
  644 to 660 -> 736 [1] lasti
  662 to 714 -> 726 [1] lasti
  726 to 734 -> 736 [1] lasti

Disassembly of <code object _update at 0x000001CAC3E52870, file "app\services\call_session_manager.py", line 168>:
              0 COPY_FREE_VARS           5

168           2 RESUME                   0

169           4 NOP

170           6 LOAD_DEREF               3 (db)
              8 LOAD_ATTR                1 (NULL|self + table)
             28 LOAD_CONST               1 ('calls')
             30 CALL                     1
             38 LOAD_ATTR                3 (NULL|self + update)

171          58 LOAD_CONST               2 ('completed')

172          60 LOAD_DEREF               2 (context)
             62 LOAD_CONST               3 ('ended_at')
             64 BINARY_SUBSCR

173          68 LOAD_DEREF               4 (duration)

174          70 LOAD_DEREF               5 (reason)

175          72 LOAD_DEREF               4 (duration)

170          74 LOAD_CONST               4 (('status', 'ended_at', 'duration_seconds', 'end_reason', 'actual_duration'))
             76 BUILD_CONST_KEY_MAP      5
             78 CALL                     1

176          86 LOAD_ATTR                5 (NULL|self + eq)
            106 LOAD_CONST               5 ('call_uuid')
            108 LOAD_DEREF               1 (call_uuid)
            110 CALL                     2
            118 LOAD_ATTR                7 (NULL|self + execute)
            138 CALL                     0
            146 POP_TOP
            148 RETURN_CONST             0 (None)
        >>  150 PUSH_EXC_INFO

177         152 LOAD_GLOBAL              8 (Exception)
            162 CHECK_EXC_MATCH
            164 POP_JUMP_IF_FALSE       37 (to 240)
            166 STORE_FAST               0 (e)

178         168 LOAD_GLOBAL             10 (logger)
            178 LOAD_ATTR               13 (NULL|self + error)
            198 LOAD_CONST               6 ('[CallSessionManager] DB update error on end_call ')
            200 LOAD_DEREF               1 (call_uuid)
            202 FORMAT_VALUE             0
            204 LOAD_CONST               7 (': ')
            206 LOAD_FAST                0 (e)
            208 FORMAT_VALUE             0
            210 BUILD_STRING             4
            212 CALL                     1
            220 POP_TOP
            222 POP_EXCEPT
            224 LOAD_CONST               0 (None)
            226 STORE_FAST               0 (e)
            228 DELETE_FAST              0 (e)
            230 RETURN_CONST             0 (None)
        >>  232 LOAD_CONST               0 (None)
            234 STORE_FAST               0 (e)
            236 DELETE_FAST              0 (e)
            238 RERAISE                  1

177     >>  240 RERAISE                  0
        >>  242 COPY                     3
            244 POP_EXCEPT
            246 RERAISE                  1
ExceptionTable:
  6 to 146 -> 150 [0]
  150 to 166 -> 242 [1] lasti
  168 to 220 -> 232 [1] lasti
  232 to 240 -> 242 [1] lasti

      Disassembling code object: _update at app\services\call_session_manager.py
      Constants: (None, 'calls', 'completed', 'ended_at', ('status', 'ended_at', 'duration_seconds', 'end_reason', 'actual_duration'), 'call_uuid', '[CallSessionManager] DB update error on end_call ', ': ')
      Names: ('table', 'update', 'eq', 'execute', 'Exception', 'logger', 'error')
      Varnames: ('e',)
              0 COPY_FREE_VARS           5

168           2 RESUME                   0

169           4 NOP

170           6 LOAD_DEREF               3 (db)
              8 LOAD_ATTR                1 (NULL|self + table)
             28 LOAD_CONST               1 ('calls')
             30 CALL                     1
             38 LOAD_ATTR                3 (NULL|self + update)

171          58 LOAD_CONST               2 ('completed')

172          60 LOAD_DEREF               2 (context)
             62 LOAD_CONST               3 ('ended_at')
             64 BINARY_SUBSCR

173          68 LOAD_DEREF               4 (duration)

174          70 LOAD_DEREF               5 (reason)

175          72 LOAD_DEREF               4 (duration)

170          74 LOAD_CONST               4 (('status', 'ended_at', 'duration_seconds', 'end_reason', 'actual_duration'))
             76 BUILD_CONST_KEY_MAP      5
             78 CALL                     1

176          86 LOAD_ATTR                5 (NULL|self + eq)
            106 LOAD_CONST               5 ('call_uuid')
            108 LOAD_DEREF               1 (call_uuid)
            110 CALL                     2
            118 LOAD_ATTR                7 (NULL|self + execute)
            138 CALL                     0
            146 POP_TOP
            148 RETURN_CONST             0 (None)
        >>  150 PUSH_EXC_INFO

177         152 LOAD_GLOBAL              8 (Exception)
            162 CHECK_EXC_MATCH
            164 POP_JUMP_IF_FALSE       37 (to 240)
            166 STORE_FAST               0 (e)

178         168 LOAD_GLOBAL             10 (logger)
            178 LOAD_ATTR               13 (NULL|self + error)
            198 LOAD_CONST               6 ('[CallSessionManager] DB update error on end_call ')
            200 LOAD_DEREF               1 (call_uuid)
            202 FORMAT_VALUE             0
            204 LOAD_CONST               7 (': ')
            206 LOAD_FAST                0 (e)
            208 FORMAT_VALUE             0
            210 BUILD_STRING             4
            212 CALL                     1
            220 POP_TOP
            222 POP_EXCEPT
            224 LOAD_CONST               0 (None)
            226 STORE_FAST               0 (e)
            228 DELETE_FAST              0 (e)
            230 RETURN_CONST             0 (None)
        >>  232 LOAD_CONST               0 (None)
            234 STORE_FAST               0 (e)
            236 DELETE_FAST              0 (e)
            238 RERAISE                  1

177     >>  240 RERAISE                  0
        >>  242 COPY                     3
            244 POP_EXCEPT
            246 RERAISE                  1
ExceptionTable:
  6 to 146 -> 150 [0]
  150 to 166 -> 242 [1] lasti
  168 to 220 -> 232 [1] lasti
  232 to 240 -> 242 [1] lasti

    Disassembling code object: register_cleanup_callback at app\services\call_session_manager.py
    Constants: (None,)
    Names: ('cleanup_callbacks',)
    Varnames: ('self', 'call_uuid', 'callback')
183           0 RESUME                   0

184           2 LOAD_FAST                2 (callback)
              4 LOAD_FAST                0 (self)
              6 LOAD_ATTR                0 (cleanup_callbacks)
             26 LOAD_FAST                1 (call_uuid)
             28 STORE_SUBSCR
             32 RETURN_CONST             0 (None)

    Disassembling code object: cleanup_call at app\services\call_session_manager.py
    Constants: ('\n        Performs in-memory cleanup to avoid leaks, and triggers registered callback.\n        ', '[CallSessionManager] Cleaning up call ', None, '[CallSessionManager] Error during cleanup callback for ', ': ', '[CallSessionManager] Cleaned up in-memory call context for ')
    Names: ('logger', 'info', 'cleanup_callbacks', 'pop', 'Exception', 'error', 'active_calls')
    Varnames: ('self', 'call_uuid', 'callback', 'e')
186           0 RESUME                   0

190           2 LOAD_GLOBAL              0 (logger)
             12 LOAD_ATTR                3 (NULL|self + info)
             32 LOAD_CONST               1 ('[CallSessionManager] Cleaning up call ')
             34 LOAD_FAST                1 (call_uuid)
             36 FORMAT_VALUE             0
             38 BUILD_STRING             2
             40 CALL                     1
             48 POP_TOP

193          50 LOAD_FAST                0 (self)
             52 LOAD_ATTR                4 (cleanup_callbacks)
             72 LOAD_ATTR                7 (NULL|self + pop)
             92 LOAD_FAST                1 (call_uuid)
             94 LOAD_CONST               2 (None)
             96 CALL                     2
            104 STORE_FAST               2 (callback)

194         106 LOAD_FAST                2 (callback)
            108 POP_JUMP_IF_FALSE        9 (to 128)

195         110 NOP

196         112 PUSH_NULL
            114 LOAD_FAST                2 (callback)
            116 LOAD_FAST                1 (call_uuid)
            118 CALL                     1
            126 POP_TOP

201     >>  128 LOAD_FAST                0 (self)
            130 LOAD_ATTR               12 (active_calls)
            150 LOAD_ATTR                7 (NULL|self + pop)
            170 LOAD_FAST                1 (call_uuid)
            172 LOAD_CONST               2 (None)
            174 CALL                     2
            182 POP_TOP

202         184 LOAD_GLOBAL              0 (logger)
            194 LOAD_ATTR                3 (NULL|self + info)
            214 LOAD_CONST               5 ('[CallSessionManager] Cleaned up in-memory call context for ')
            216 LOAD_FAST                1 (call_uuid)
            218 FORMAT_VALUE             0
            220 BUILD_STRING             2
            222 CALL                     1
            230 POP_TOP
            232 RETURN_CONST             2 (None)
        >>  234 PUSH_EXC_INFO

197         236 LOAD_GLOBAL              8 (Exception)
            246 CHECK_EXC_MATCH
            248 POP_JUMP_IF_FALSE       37 (to 324)
            250 STORE_FAST               3 (e)

198         252 LOAD_GLOBAL              0 (logger)
            262 LOAD_ATTR               11 (NULL|self + error)
            282 LOAD_CONST               3 ('[CallSessionManager] Error during cleanup callback for ')
            284 LOAD_FAST                1 (call_uuid)
            286 FORMAT_VALUE             0
            288 LOAD_CONST               4 (': ')
            290 LOAD_FAST                3 (e)
            292 FORMAT_VALUE             0
            294 BUILD_STRING             4
            296 CALL                     1
            304 POP_TOP
            306 POP_EXCEPT
            308 LOAD_CONST               2 (None)
            310 STORE_FAST               3 (e)
            312 DELETE_FAST              3 (e)
            314 JUMP_BACKWARD           94 (to 128)
        >>  316 LOAD_CONST               2 (None)
            318 STORE_FAST               3 (e)
            320 DELETE_FAST              3 (e)
            322 RERAISE                  1

197     >>  324 RERAISE                  0
        >>  326 COPY                     3
            328 POP_EXCEPT
            330 RERAISE                  1
ExceptionTable:
  112 to 126 -> 234 [0]
  234 to 250 -> 326 [1] lasti
  252 to 304 -> 316 [1] lasti
  316 to 324 -> 326 [1] lasti
